Workbook

Sheet To do
H1: Lot 2, Trumbull - | K1: Questions | M1: Drawing
A2: Structural | B2: Rosenberg | C2: krystals@racivil.com | H2: 435-218-9510 | K2: Ceiling/Wall | M2: Manual J&D | O2: emailed
A3: Geo | B3: Gem | C3: brennan@gemenginc.com | K3: Niche | M3: Jones
A4: Permit | H4: Lot 3, Casey- 435-229-7948 | M4: Fitures
A5: Survey | M5: fans
A6: Sign | H6: Trumbell Bundy | K6: Wall Tile | M6: Switch legs
H7: 435 218 9510 | K7: Vanity mirror | M7: Panel Calcs
A8: Road Prep | B8: Dom Klesch | E8: 435-463-8210 | F8: Seth Newtson | K8: 120 Fixture problems | M8: Switching
A9: Well | B9: Dom Klesch | H9: Todd | K9: Wood floor Adu Closet | M9: Topo/Grading
A10: Power | B10: Dom Klesch | H10: 435 705 4264
A11: Gas | B11: Dom Klesch | K11: .
A12: Septic | B12: Dom Klesch
A13: Internet | B13: Dom Klesch
A15: Temp Facilities
A16: Excavation/Pad Prep/Backfill
A17: Concrete | B17: Randy Frie
A18: Foundatin Wall | B18: Randy Frie
A19: WaterProffing
A20: Termite
A22: Steel | B22: D Iron works
A23: Truss | B23: Sunpro | C23: smitcheel@sunpro.com
A24: Framing Material | B24: Sunroc | C24: smitcheel@sunpro.com
A25: Framing Labor | B25: Elwin | C25: gieframing502@gmail.com
A26: Stair
A28: EXT Doors | B28: Sunpro | C28: srmitchel@sunpro.com
A29: Windows | B29: STG | C29: nathan@lpbuildingsolutions.com
A30: Glass | B30: STG
A31: Roofing
A32: Roof Deck
A33: Roof Metal
A34: Stucco | B34: Simco
A35: Stone | B35: Simco
A36: Rammed Earth | B36: Clayworks | C36: ger@clay-works.com | E36: Allysa Oliver
A37: Rammed Earth Labor | B37: Woodland Stucco | C37: woodlandstuccoandpaint@gmail.com | F37: 30 int 40 Ex | H37: Labor only
A39: Mechanical | B39: Dash
A40: Plumbing | B40: Master | C40: office@masterplumbingsystems.com
A41: Gas | B41: Master | C41: office@masterplumbingsystems.com
A42: Plumbing Fixtures
A43: Electrical | B43: Dash
A44: Electrical Fixtures
A45: Solar
A46: Solar Material
A47: Fireplace
A49: Insulation | B49: LP | C49: nathan@lpbuildingsolutions.com
A50: Drywall | B50: H&E | C50: hedrywall1022@gmail.com | E50: 5.7 | F50: House | H50: Gawal
A51: Plaster | B51: Simco | E51: 5.5 | F51: Stucco
A52: Paint | B52: Jose | C52: woodlandstuccoandpaint@gmail.com | E52: 3.3 | F52: House
A53: Garage Door | B53: Sunroc | C53: srmitchel@sunpro.com
A54: Flooring Material | B54: G&S
A55: Flooring labor | B55: G&S | I55: Doors | K55: 30
A56: Int Doors | B56: Sunroc
A57: Hidden door
A58: Vault Door
A59: Base | B59: Sunroc
A60: Hardware | B60: Sunroc | C60: srmitchel@sunpro.com
A61: Carpentry | B61: A&L | C61: ammon@a&lfinish
A62: Cabinet | B62: Deez | C62: deezcabnuts@gmail.com | E62: rrcabinetsinc@gmail.com
A63: Closet
A64: Tile Material
A65: Tile Labor | B65: G&S
A66: Floor Heat
A67: Steam
A68: Clayworks
A69: Countertop | B69: Countertop Source
A70: Bath Hardware
A71: Mirrors & Specialty Glass
A72: Appliance | B72: Boulevard | C72: haley.benware@blvdhome.com
A73: AV
A74: Range | B74: Chris | C74: chrishr@actiontarget.com
A76: Railing | C76: Broken Horn
A77: Landscape/Drive
A78: Pavers

Sheet Budget1
A1: Who is it Yes I meet that bunch of real cast like you know you got to watch you I this guy Got fucking indigestion from the sugar Yep Well yeah I feel like I know I've stabbed you you It's not too long that's just not fair to me Oh Whoops | B1: 646 W Liberty Lane | C1: =B4-C4 -> -7255.149 | D1: AKA 1025 S | E1: Kannerrville | F1: 84742
C2: 0.1
A3: Sq Ft | B3: =sum(L24:L28) -> 6993 | C3: Budget | D3: Budget | E3: CPF | F3: Duration | G3: Completion | I3: Pay Schedule | K3: Profit
A4: Build Gross | B4: =sum(B6:B92) -> 2846193.4 | C4: =sum(C7:C92) -> 2853448.5 | D4: =sum(D7:D92) -> 3088193.4 | E4: =sum(E20:E92) -> 363.66986 | F4: =sum(F5:F92) -> 383 | G4: =G92 -> 46127 | I4: =sum(I7:I95) -> 3089193.4 | K4: =C4-D4 -> -234744.85
A6: Deposit | B6: =sum(D7:D18) -> 545050 | L6: =I26 -> 603350 | M6: Cost to permit/deposit
A7: Plumbing Fixtures | B7: RAC | C7: 17000 | D7: =(C7*$C$2)+C7 -> 18700 | E7: =D7/$B$3 -> 2.6741027 | G7: 45689 | L7: =I32 -> 242000 | M7: 45991
A8: Electrical Fixtures | B8: RAC | C8: 18000 | D8: =(C8*$C$2)+C8 -> 19800 | E8: =D8/$B$3 -> 2.8314028 | G8: 45689 | L8: =I37 | M8: 46021
A9: Hidden Door | C9: 25000 | D9: =(C9*$C$2)+C9 -> 27500 | E9: =D9/$B$3 -> 3.9325039 | G9: 45689 | L9: =I39 -> 1000 | M9: 46052
A10: Vault Door | C10: 7500 | D10: =(C10*$C$2)+C10 -> 8250 | E10: =D10/$B$3 -> 1.1797512 | G10: 45689 | L10: =I41 | M10: 46081
A11: Cabinet | B11: Deez | C11: 26000 | D11: =(C11*$C$2)+C11 -> 28600 | E11: =D11/$B$3 -> 4.0898041 | G11: 45689 | L11: =I43 -> 187660 | M11: 46111
A12: Entry Stair | B12: TGC | C12: 17000 | D12: =(C12*$C$2)+C12 -> 18700 | E12: =D12/$B$3 -> 2.6741027 | G12: 45689 | L12: =I53 -> 262900 | M12: 46142
A13: Tile Material | B13: RAC | C13: 80000 | D13: =(C13*$C$2)+C13 -> 88000 | E13: =D13/$B$3 -> 12.584013 | G13: 45689 | L13: =I61 -> 415800 | M13: 46172
A14: Rammed Earth | B14: Alysa Oliver | C14: 50000 | D14: =(C14*$C$2)+C14 -> 55000 | E14: =D14/$B$3 -> 7.8650079 | G14: 45689 | L14: =I62 -> 78650 | M14: 46203
A15: Exterior Glass | B15: STG | C15: 115000 | D15: =(C15*$C$2)+C15 -> 126500 | E15: =D15/$B$3 -> 18.089518 | G15: 45689 | L15: =I73 -> 296450 | M15: 46233
A16: Rammed earth Material | B16: Clayworks | C16: 45000 | D16: =(C16*$C$2)+C16 -> 49500 | E16: =D16/$B$3 -> 7.0785071 | G16: 45689 | L16: =I81 -> 243100 | M16: 46264
A17: Railing | C17: 46000
A18: Range | B18: Action Target | C18: 95000 | D18: =(C18*$C$2)+C18 -> 104500 | E18: =D18/$B$3 -> 14.943515 | G18: 45689 | L18: =I87 -> 287650 | M18: 46295
A19: Permiting | B19: =sum(D20:D26) -> 58300 | L19: =I89 -> 27500 | M19: 46325
A20: Facilities | C20: 10000 | D20: =(C20*$C$2)+C20 -> 11000 | E20: =D20/$B$3 -> 1.5730016 | G20: 45689 | L20: =I91 -> 30800 | M20: 46356
A21: Permits | B21: Iron County | C21: 30000 | D21: =(C21*$C$2)+C21 -> 33000 | E21: =D21/$B$3 -> 4.7190047 | G21: 45690 | K21: Total | L21: =sum(L6:L20) -> 2676860
A22: Builders Risk | C22: 5000 | D22: =(C22*$C$2)+C22 -> 5500 | E22: =D22/$B$3 -> 0.78650079 | G22: 45691
A23: Manual J | C23: 1500 | D23: =(C23*$C$2)+C23 -> 1650 | E23: =D23/$B$3 -> 0.23595024 | G23: 45692
A24: Plans | B24: Steamroller | C24: 1000 | D24: =(C24*$C$2)+C24 -> 1100 | E24: =D24/$B$3 -> 0.15730016 | G24: 45693 | L24: 2181
A25: Soil | B25: Gem | C25: 3000 | D25: =(C25*$C$2)+C25 -> 3300 | E25: =D25/$B$3 -> 0.47190047 | G25: 45694 | L25: 409
A26: Inspections | C26: 2500 | D26: =(C26*$C$2)+C26 -> 2750 | E26: =D26/$B$3 -> 0.39325039 | G26: 45695 | I26: =B6+B19 -> 603350 | L26: 2206
A27: Site Utilities | B27: All right | L27: 919
A28: Site Utilities | C28: 122000 | D28: =(C28*$C$2)+C28 -> 134200 | E28: =D28/$B$3 -> 19.190619 | F28: 7 | G28: =WORKDAY(G26, F28) -> 45706 | L28: 1278
A29: Road | C29: 78000 | D29: =(C29*$C$2)+C29 -> 85800 | E29: =D29/$B$3 -> 12.269412 | F29: 14 | G29: =WORKDAY(G28, F29) -> 45726
A30: Gas | B30: RAC | C30: 10000 | D30: =(C30*$C$2)+C30 -> 11000 | E30: =D30/$B$3 -> 1.5730016 | F30: 2 | G30: =WORKDAY(G29, F30) -> 45728
A31: Power | C31: 5000 | D31: =(C31*$C$2)+C31 -> 5500 | E31: =D31/$B$3 -> 0.78650079 | F31: 5 | G31: =WORKDAY(G30, F31) -> 45735 | L31: 1979
A32: Water | C32: 5000 | D32: =(C32*$C$2)+C32 -> 5500 | E32: =D32/$B$3 -> 0.78650079 | F32: 4 | G32: =WORKDAY(G31, F32) -> 45741 | I32: =sum(D28:D32) -> 242000 | L32: 3229
A33: Structural | B33: =sum(D34:D43) -> 599993.36 | L33: =sum(L31:L32) -> 5208 | M33: =(D53+D85)/L33 -> 31.259601
A34: Ftgs | B34: Frie | C34: 35710.41 | D34: =(C34*$C$2)+C34 -> 39281.451 | E34: =D34/$B$3 -> 5.6172531 | F34: 7 | G34: =WORKDAY(G32, F34) -> 45750
A35: Wall | B35: Frie | C35: 63078 | D35: =(C35*$C$2)+C35 -> 69385.8 | E35: =D35/$B$3 -> 9.9221793 | F35: 7 | G35: =WORKDAY(G34, F35) -> 45761
A36: Slab | B36: Frie | C36: 49345.1 | D36: =(C36*$C$2)+C36 -> 54279.61 | E36: =D36/$B$3 -> 7.761992 | F36: 7 | G36: =WORKDAY(G35, F36) -> 45770
A37: Pan | B37: Frie | C37: 32075 | D37: =(C37*$C$2)+C37 -> 35282.5 | E37: =D37/$B$3 -> 5.0454025 | F37: 7 | G37: =WORKDAY(G36, F37) -> 45779
A38: Site | B38: Frie | C38: 9640 | D38: =(C38*$C$2)+C38 -> 10604 | E38: =D38/$B$3 -> 1.5163735 | F38: 7 | G38: =WORKDAY(G37, F38) -> 45790 | I38: =sum(D34:D38) -> 208833.36
A39: Pretreat | B39: RAC | C39: 1000 | D39: =(C39*$C$2)+C39 -> 1100 | E39: =D39/$B$3 -> 0.15730016 | F39: 7 | G39: =WORKDAY(G37, F39) -> 45790 | I39: =C39 -> 1000
A40: Steel | B40: D-Iron Works | C40: 184000 | D40: =(C40*$C$2)+C40 -> 202400 | E40: =D40/$B$3 -> 28.943229 | F40: 27 | G40: =WORKDAY(G39, F40) -> 45827 | I40: =C40 -> 184000
A41: Lumber | B41: Sunpro | C41: 50000 | D41: =(C41*$C$2)+C41 -> 55000 | E41: =D41/$B$3 -> 7.8650079 | G41: =WORKDAY(G40, F41) -> 45827
A42: Framing Labor | B42: DAG | C42: 80600 | D42: =(C42*$C$2)+C42 -> 88660 | E42: =D42/$B$3 -> 12.678393 | F42: 27 | G42: =WORKDAY(G41, F42) -> 45866
A43: Truss | B43: SunPro | C43: 40000 | D43: =(C43*$C$2)+C43 -> 44000 | E43: =D43/$B$3 -> 6.2920063 | G43: =WORKDAY(G42, F43) -> 45866 | I43: =sum(D41:D43) -> 187660
A44: Mechanical Rough | B44: =sum(D45:D50) -> 252450
A45: HVAC/ERV | B45: Dash | C45: 32000 | D45: =(C45*$C$2)+C45 -> 35200 | E45: =D45/$B$3 -> 5.033605 | F45: 5 | G45: =WORKDAY(G43, F45) -> 45873
A46: Plumbing/Gas | B46: Master | C46: 25000 | D46: =(C46*$C$2)+C46 -> 27500 | E46: =D46/$B$3 -> 3.9325039 | F46: 5 | G46: =WORKDAY(G45, F46) -> 45880
A47: Electrical | B47: DAsh | C47: 45000 | D47: =(C47*$C$2)+C47 -> 49500 | E47: =D47/$B$3 -> 7.0785071 | F47: 10 | G47: =WORKDAY(G46, F47) -> 45894
A48: AV | B48: Tek it | C48: 80000 | D48: =(C48*$C$2)+C48 -> 88000 | E48: =D48/$B$3 -> 12.584013 | F48: 5 | G48: =WORKDAY(G47, F48) -> 45901
A49: Solar | B49: Raven | C49: 25000 | D49: =(C49*$C$2)+C49 -> 27500 | E49: =D49/$B$3 -> 3.9325039 | G49: =WORKDAY(G48, F49) -> 45901
A50: Fireplace | B50: Master | C50: 22500 | D50: =(C50*$C$2)+C50 -> 24750 | E50: =D50/$B$3 -> 3.5392535 | F50: 1 | G50: =WORKDAY(G49, F50) -> 45902
A51: Exterior Sealing | B51: =sum(D52:D59) -> 470250
A52: Roofing | B52: RAC | C52: 35000 | D52: =(C52*$C$2)+C52 -> 38500 | E52: =D52/$B$3 -> 5.5055055 | F52: 7 | G52: =WORKDAY(G43, F52) -> 45875
A53: Coatings | B53: Advance | C53: 102000 | D53: =(C53*$C$2)+C53 -> 112200 | E53: =D53/$B$3 -> 16.044616 | F53: 14 | G53: =WORKDAY(G52, F53) -> 45895 | I53: =sum(D45:D47)+sum(D52:D53) -> 262900
A54: Exterior Glass | B54: STG | C54: 115000 | D54: =(C54*$C$2)+C54 -> 126500 | E54: =D54/$B$3 -> 18.089518 | F54: 14 | G54: =WORKDAY(G53, F54) -> 45915
A55: Exterior Doors | B55: Sunroc | C55: 13000 | D55: =(C55*$C$2)+C55 -> 14300 | E55: =D55/$B$3 -> 2.044902 | F55: 2 | G55: =WORKDAY(G54, F55) -> 45917
A56: Garage Door | B56: Sunroc | C56: 22500 | D56: =(C56*$C$2)+C56 -> 24750 | E56: =D56/$B$3 -> 3.5392535 | F56: 5 | G56: =WORKDAY(G55, F56) -> 45924
A57: Exterior Stucco | B57: Simco | C57: 60000 | D57: =(C57*$C$2)+C57 -> 66000 | E57: =D57/$B$3 -> 9.4380094 | G57: =WORKDAY(G56, F57) -> 45924
A58: Stone Veneer | B58: Simco | C58: 30000 | D58: =(C58*$C$2)+C58 -> 33000 | E58: =D58/$B$3 -> 4.7190047 | F58: 5 | G58: =WORKDAY(G57, F58) -> 45931
A59: Rammed Earth | B59: Alysa Oliver | C59: 50000 | D59: =(C59*$C$2)+C59 -> 55000 | E59: =D59/$B$3 -> 7.8650079 | F59: 21 | G59: =WORKDAY(G58, F59) -> 45960
A60: Wall/Cieling Finish | B60: =sum(D61:D64) -> 173250
A61: Insulation | B61: LP | C61: 40000 | D61: =(C61*$C$2)+C61 -> 44000 | E61: =D61/$B$3 -> 6.2920063 | F61: 2 | G61: =WORKDAY(G50, F61) -> 45904 | I61: =sum(D48:D50)+sum(D54:D57)+D61 -> 415800
A62: Sheetrock | B62: H&E | C62: 41500 | D62: =(C62*$C$2)+C62 -> 45650 | E62: =D62/$B$3 -> 6.5279565 | F62: 28 | G62: =WORKDAY(G61, F62) -> 45944 | I62: =D58+D62 -> 78650
A63: Paint | B63: Jose | C63: 23000 | D63: =(C63*$C$2)+C63 -> 25300 | E63: =D63/$B$3 -> 3.6179036 | F63: 14 | G63: =WORKDAY(G62, F63) -> 45964
A64: Tile Labor | B64: GS | C64: 53000 | D64: =(C64*$C$2)+C64 -> 58300 | E64: =D64/$B$3 -> 8.3369083 | G64: =WORKDAY(G63, F64) -> 45964
A65: Carpentery | B65: =sum(D66:D76) -> 204600
A66: Cabinet | B66: Deez | C66: 26000 | D66: =(C66*$C$2)+C66 -> 28600 | E66: =D66/$B$3 -> 4.0898041 | F66: 3 | G66: =WORKDAY(G64, F66) -> 45967
A67: Countertops | B67: Countertop source | C67: 45000 | D67: =(C67*$C$2)+C67 -> 49500 | E67: =D67/$B$3 -> 7.0785071 | F67: 1 | G67: =WORKDAY(G66, F67) -> 45968
A68: Finish Carpentry | B68: A&L | C68: 12000 | D68: =(C68*$C$2)+C68 -> 13200 | E68: =D68/$B$3 -> 1.8876019 | F68: 5 | G68: =WORKDAY(G67, F68) -> 45975
A69: Door | B69: Sunpro | C69: 28500 | D69: =(C69*$C$2)+C69 -> 31350 | E69: =D69/$B$3 -> 4.4830545 | F69: 5 | G69: =WORKDAY(G68, F69) -> 45982
A70: Base&Case | B70: Sunpro | C70: 5000 | D70: =(C70*$C$2)+C70 -> 5500 | E70: =D70/$B$3 -> 0.78650079 | G70: =WORKDAY(G69, F70) -> 45982
A71: Door & Bath Hardware | B71: Sunpro | C71: 5000 | D71: =(C71*$C$2)+C71 -> 5500 | E71: =D71/$B$3 -> 0.78650079 | F71: 2 | G71: =WORKDAY(G70, F71) -> 45986
A72: Entry Stair | B72: TGC | C72: 17000 | D72: =(C72*$C$2)+C72 -> 18700 | E72: =D72/$B$3 -> 2.6741027 | G72: =WORKDAY(G71, F72) -> 45986
A73: Wood Stair | B73: RAC | C73: 5000 | D73: =(C73*$C$2)+C73 -> 5500 | E73: =D73/$B$3 -> 0.78650079 | F73: 2 | G73: =WORKDAY(G72, F73) -> 45988 | I73: =sum(D63:D73)+D59 -> 296450
A74: Stair Labor | B74: RAC | C74: 10000 | D74: =(C74*$C$2)+C74 -> 11000 | E74: =D74/$B$3 -> 1.5730016 | F74: 2 | G74: =WORKDAY(G73, F74) -> 45992
A75: Vault Door | B75: RAC | C75: 7500 | D75: =(C75*$C$2)+C75 -> 8250 | E75: =D75/$B$3 -> 1.1797512 | F75: 2 | G75: =WORKDAY(G74, F75) -> 45994
A76: Hidden Door | C76: 25000 | D76: =(C76*$C$2)+C76 -> 27500 | E76: =D76/$B$3 -> 3.9325039 | F76: 2 | G76: =WORKDAY(G75, F76) -> 45996
A77: Equipment/ Finishes | B77: =sum(D78:D87) -> 484000
A78: HVAC/ERV | C78: 21500 | D78: =(C78*$C$2)+C78 -> 23650 | E78: =D78/$B$3 -> 3.3819534 | F78: 3 | G78: =WORKDAY(G76, F78) -> 46001
A79: Plumbing/Gas | B79: Master | C79: =C45 -> 32000 | D79: =(C79*$C$2)+C79 -> 35200 | E79: =D79/$B$3 -> 5.033605 | F79: 3 | G79: =WORKDAY(G78, F79) -> 46006
A80: Electrical | B80: RAC | C80: 45000 | D80: =(C80*$C$2)+C80 -> 49500 | E80: =D80/$B$3 -> 7.0785071 | F80: 3 | G80: =WORKDAY(G79, F80) -> 46009
A81: AV | B81: Tek it | C81: 80000 | D81: =(C81*$C$2)+C81 -> 88000 | E81: =D81/$B$3 -> 12.584013 | F81: 5 | G81: =WORKDAY(G80, F81) -> 46016 | I81: =sum(D74:D81) -> 243100
A82: Range | B82: Action Target | C82: 95000 | D82: =(C82*$C$2)+C82 -> 104500 | E82: =D82/$B$3 -> 14.943515 | F82: 7 | G82: =WORKDAY(G81, F82) -> 46027
A83: Appliance | B83: Blvd | C83: 48000 | D83: =(C83*$C$2)+C83 -> 52800 | E83: =D83/$B$3 -> 7.5504076 | F83: 1 | G83: =WORKDAY(G82, F83) -> 46028
A84: Glass | B84: RAC | C84: 7500 | D84: =(C84*$C$2)+C84 -> 8250 | E84: =D84/$B$3 -> 1.1797512 | F84: 2 | G84: =WORKDAY(G83, F84) -> 46030
A85: Railing | B85: Broken Horn | C85: =C17 -> 46000 | D85: =(C85*$C$2)+C85 -> 50600 | E85: =D85/$B$3 -> 7.2358072 | F85: 5 | G85: =WORKDAY(G84, F85) -> 46037
A86: Outdoor | B86: RAC | C86: 60000 | D86: =(C86*$C$2)+C86 -> 66000 | E86: =D86/$B$3 -> 9.4380094 | F86: 5 | G86: =WORKDAY(G85, F86) -> 46044
A87: Cleaning | B87: RAC | C87: 5000 | D87: =(C87*$C$2)+C87 -> 5500 | E87: =D87/$B$3 -> 0.78650079 | F87: 3 | G87: =WORKDAY(G86, F87) -> 46049 | I87: =sum(D82:D87) -> 287650
A88: Landscape | B88: =sum(D89:D91) -> 58300 | G88: `
A89: Solar | B89: Raven | C89: 25000 | D89: =(C89*$C$2)+C89 -> 27500 | E89: =D89/$B$3 -> 3.9325039 | F89: 4 | G89: =WORKDAY(G87, F89) -> 46055 | I89: =D89 -> 27500
A90: Landscape | B90: RAC | D90: =(C90*$C$2)+C90 -> 0 | E90: =D90/$B$3 -> 0 | F90: 21 | G90: =WORKDAY(G89, F90) -> 46084
A91: Pavers | B91: RAC | C91: 28000 | D91: =(C91*$C$2)+C91 -> 30800 | E91: =D91/$B$3 -> 4.4044044 | F91: 10 | G91: =WORKDAY(G90, F91) -> 46098 | I91: =sum(D90:D91) -> 30800
A92: Contingency | E92: =D92/$B$3 -> 0 | F92: 21 | G92: =WORKDAY(G91, F92) -> 46127
A93: Options | G93: =G92+F93 -> 46127
A94: Steam | B94: RAC | I94: 12000
A95: Floor Heat | B95: RAC | I95: 7500

Sheet Sheet29
A2: ex | B2: Supply Prropne tank
B3: spec waterr collection tank
B4: include water pipe to collection
B5: spec waterr collection tank
B6: well tie in need add

Sheet Fixtures
A1: That's it | G1: Flooring | M1: Electircal Fixtures | P1: Flooring/Tile | S1: AV | V1: Solar
A2: Sinks | G2: Paver | H2: 2470 | I2: 11 | J2: =H2*I2 -> 27170
A3: Glacier Bay 33 | B3: 2 | C3: 300 | D3: Kitchen | G3: Pergo | H3: 1172 | I3: 3 | J3: =H3*I3 -> 3516
A4: Horrow Undermount | C4: 120 | D4: ADU | G4: Nashville | H4: 2636 | I4: 9 | J4: =H4*I4 -> 23724
A5: Horrow Undermount | C5: 120 | D5: Powder | G5: Carpet | H5: 950 | I5: 3 | J5: =H5*I5 -> 2850
A6: Horrow Undermount | C6: 120 | D6: Office | G6: Carra | H6: 783 | I6: 9 | J6: =H6*I6 -> 7047
A7: Horrow Undermount | C7: 120 | D7: ADU | G7: Wall Tile | H7: 755 | I7: 20 | J7: =H7*I7 -> 15100
A8: Horrow Undermount | C8: 240 | D8: Primary | G8: concrete Tile | H8: 600 | I8: 20 | J8: =H8*I8 -> 12000
A9: Mop Sink | C9: 319 | E9: Wand?
A10: Faucet | G10: Total | J10: =SUM(J2:J8) -> 91407
A11: Kohler Crue Touchless | B11: 2 | C11: 900 | D11: Kitchen
A12: Arc Waterfall | C12: 50 | D12: ADU | G12: Labor Floor | H12: =H3+H4+H6 -> 4591 | I12: 6 | J12: =H12*I12 -> 27546
A13: Arc Waterfall | C13: 50 | D13: Powder | G13: Labor Wall | H13: =H7+H8 -> 1355 | I13: 16 | J13: =H13*I13 -> 21680
A14: Arc Waterfall | C14: 50 | D14: Office | G14: Carpet | H14: =H5 -> 950 | I14: 3 | J14: =H14*I14 -> 2850
A15: Arc Waterfall | C15: 50 | D15: ADU
A16: Arc Waterfall | C16: 100 | D16: Primary | G16: total | J16: =sum(J12:J14) -> 52076
A17: Moen Wall Mount | C17: 140 | D17: Garage
A18: Toilet
A19: Horrow Unique | B19: 6 | C19: 6000
A20: Shower Valve
A21: Granjoy | B21: 3 | C21: 3000
A22: Tub | C22: 3500
A23: Tub Filler | C23: 1000
A24: Drains
A25: Oatey 24" Linear | B25: 3 | C25: 375
A26: Total | C26: =sum(C3:C25) -> 16554

Sheet Appliance
A2: Kitchen
A3: Appliance site | B3: http://www.thermador.com/
A4: 36" Refridge Column | B4: https://www.thermador.com/us/en/mkt-product/refrigeration/refrigerationrefrigerationcolumns/T36IR905SP
A5: 36" Freezer Column | B5: https://www.thermador.com/us/en/mkt-product/refrigeration/freezer-columns/T36IF905SP
A6: Double Oven | B6: https://www.thermador.com/us/en/mkt-product/ovens/double-ovens/MEDMC301WS
A7: Dishwasher | B7: https://www.thermador.com/us/en/mkt-product/dishwashers/custom-panel/DWHD640EPR
A8: Hood | B8: https://futurofuturo.com/54-skylight-ceiling-soffit-range-hood/?gad_source=1&gad_campaignid=22020168852&gbraid=0AAAAAD_hDAqqlhc5Adnrl7h_avAB-_94G&gclid=Cj0KCQjwxJvBBhDuARIsAGUgNfjVKi_F2Q8pLZHI8rJNJsrPAnkCamTcDZ1jcF-O4WFol61rn8Fug2caAnlzEALw_wcB
A9: Cooktop | B9: https://www.infinitysurfaces.it/invisible-induction-cooktop/
A10: Under Counter Fridge | B10: https://www.homedepot.com/p/TITTLA-24-in-Single-Zone-150-Can-Beverage-Refrigerator-in-Silver-with-2-Different-Door-Handles-Built-in-Beverage-Cooler-KMBR150/326580232
A11: Ice maker 400 | B11: https://www.homedepot.com/p/TITTLA-14-in-100-lbs-Full-Size-Ice-Cubes-per-day-Ice-Maker-with-Blue-LEDs-Interior-in-Silver-Stainless-Steel-HY45FT/326504176
A12: Ice maker 900 | B12: https://www.homedepot.com/p/COTLIN-15-in-22-lb-Built-In-Ice-Maker-in-Stainless-Steel-with-Reversible-Door-Crescent-Ice-IMC25BI/328501726
A14: ADU
A15: Package | B15: https://www.homedepot.com/p/sets/Frigidaire-25-6-cu-ft-Standard-Depth-Refrigerator-with-5-Burner-Freestanding-Electric-Range-and-Dishwasher/335525148
A16: Stack | B16: recomend
A19: Laundry | B19: recomend
A20: Washer | B20: recomend

Sheet Load
A1: What the fuck did I do with this shit man | B1: Calculated Load (A) | C1: Continuous Load x 125% | D1: Recommended Breaker | E1: Recommended Conductor (Cu) | F1: Recommended Conduit | K1: Amps
A2: Panel 1 | B2: 239 | C2: 298.8 | D2: 300 A | E2: 350 kcmil x 3 conductors + #2 AWG Ground | F2: 2.5" EMT (minimum)
A3: Panel 2 | B3: 250.5 | C3: 313.1 | D3: 300 A | E3: 350 kcmil x 3 conductors + #2 AWG Ground | F3: 2.5" EMT (minimum)
A4: Panel 3 | B4: 179.3 | C4: 224.1 | D4: 225 A | E4: 4/0 AWG x 3 conductors + #4 AWG Ground | F4: 2" EMT (minimum)
A5: Main Transformer | B5: 668.8 | C5: 836 | D5: 800 A Main | E5: Parallel 500 kcmil x 4 per phase + 1/0 Ground | F5: Dual 3" EMT runs (per phase)
A9: **TOTAL PANEL 1 LOAD**
A10: Lighting Loads | B10: Load | C10: Feet/Location | D10: Watts | E10: Load A | F10: Transformer | G10: Breaker | H10: NCL A
A11: Total | D11: =sum(D12:D53) -> 3228.9 | E11: =sum(E12:E32) -> 127.3375 | H11: =sum(H12:H32) -> 127.335
A12: Circuit 1 | B12: P1-EXT-1 | D12: 160.02 | E12: =D12/24 -> 6.6675 | F12: HDR-240-24 (10A) | G12: 7A | H12: 6.67 | I12: ShellY RGBWW Pro | J12: Dimmer
A13: Circuit 2 | B13: P1-EXT-2 | D13: 297.18 | E13: =D13/24 -> 12.3825 | F13: HDR-480-24 (20A) | G13: 15 A | H13: 12.38 | I13: ShellY RGBWW Pro | J13: Dimmer
A14: Circuit 3 | B14: P1-EXT-3 | D14: 228.6 | E14: =D14/24 -> 9.525 | F14: HDR-320-24 (13.3A) | G14: 10A | H14: 9.53 | I14: ShellY RGBWW Pro | J14: Dimmer
A15: Circuit 4 | B15: P1-EXT-4 | D15: 388.62 | E15: =D15/24 -> 16.1925 | F15: HDR-480-24 (20A) | G15: 20 A | H15: 16.19 | I15: ShellY RGBWW Pro | J15: Dimmer
A16: Circuit 5 | B16: P1-EXT-5 | D16: 274.32 | E16: =D16/24 -> 11.43 | F16: HDR-320-24 (13.3A) | G16: 15 A | H16: 11.43 | I16: ShellY RGBWW Pro | J16: Dimmer
A17: Circuit 6 | B17: P1-EXT-6 | D17: 320.04 | E17: =D17/24 -> 13.335 | F17: HDR-480-24 (20A) | G17: 15 A | H17: 13.33 | I17: ShellY RGBWW Pro | J17: Dimmer
A18: Circuit 7 | B18: P1-EXT-7 | D18: 274.32 | E18: =D18/24 -> 11.43 | F18: HDR-320-24 (13.3A) | G18: 15 A | H18: 11.43 | I18: ShellY RGBWW Pro | J18: Dimmer
A19: Circuit 8 | B19: P1-LVC-1 | C19: Kitchen Cooktop | D19: 168 | E19: =D19/24 -> 7 | F19: HDR-320-24 (13.3A) | G19: 15 A | H19: =D19/24 -> 7 | I19: ShellY RGBWW Pro | J19: Dimmer
A20: Circuit 1 | B20: P1-LVC-2 | C20: Kitchen dish Sink | D20: 72 | E20: =D20/24 -> 3 | F20: HDR-150-24 (5A) | G20: 7A | H20: =D20/24 -> 3 | I20: ShellY RGBWW Pro | J20: Dimmer
A21: Circuit 9 | B21: P1-LVC-3 | C21: Office | D21: 360 | E21: =D21/24 -> 15 | F21: HDR-480-24 (20A) | G21: 15 A | H21: =D21/24 -> 15 | I21: ShellY RGBWW Pro | J21: Dimmer
A22: Circuit 10 | B22: P1-LVM-1 | C22: Garge | D22: 36 | E22: =D22/24 -> 1.5 | F22: HDR-320-24 (20A) | G22: 15 A | H22: =sum(D22:D29)/24 -> 12 | I22: Shelly 1 PM
B23: P1-LVM-2 | C23: Systems Garage | D23: 18 | E23: =D23/24 -> 0.75 | F23: Combined 24V-10 | I23: Shelly 1 PM
B24: P1-LVM-3 | C24: Back Stair | D24: 36 | E24: =D24/24 -> 1.5 | F24: Combined 24V-10 | I24: tx | J24: Dimmer
B25: P1-LVM-4 | C25: Mechanical | D25: 18 | E25: =D25/24 -> 0.75 | F25: Combined 24V-10 | I25: Shelly 1 PM
B26: P1-LVM-5 | C26: Storage | D26: 18 | E26: =D26/24 -> 0.75 | F26: Combined 24V-10 | I26: Shelly 1 PM
B27: P1-LVM-6 | C27: Pantry | D27: 54 | E27: =D27/24 -> 2.25 | F27: Combined 24V-10 | I27: Shelly 1 PM
B28: P1-LVM-7 | C28: Office Closet | D28: 36 | E28: =D28/24 -> 1.5 | F28: Combined 24V-10 | I28: Shelly 1 PM
B29: P1-LB-8 | C29: Office Bath | D29: 72 | E29: =D29/24 -> 3 | F29: Combined 24V-10 | I29: Shelly 2 PM Pro-1.1 | J29: Dimmer
A30: Circuit 11 | B30: P1-L120-1 | C30: Powder | D30: 75 | E30: =D30/24 -> 3.125 | F30: HDR-480-24 (20A) | G30: 15 A | H30: =sum(D30:D32)/24 -> 9.375 | I30: Shelly 1 PM
B31: P1-L120-2 | C31: Island | D31: 75 | E31: =D31/24 -> 3.125 | F31: Combined 120V-11 | I31: Shelly 2 PM Pro-1.1 | J31: Dimmer
B32: P1-L120-3 | C32: Dining | D32: 75 | E32: =D32/24 -> 3.125 | F32: Combined 120V-11 | I32: Shelly 2 PM Pro-1.1 | J32: Dimmer
A33: Wall Loads
A34: Total | E34: =sum(E35:E53) -> 231.44 | H34: =sum(H35:H53) -> 294.44
A35: Circuit 12 | B35: P1-120-1 (120V) | E35: 16 | F35: 120V Circuit | G35: 40 A GFCI | H35: 16 | I35: Shelly PM-4-1.1
B36: P1-120-2 (120V) | E36: 16 | F36: 120V Circuit | H36: 16 | I36: Shelly PM-4-1.2
B37: P1-120-3 (120V) | E37: 16 | F37: 120V Circuit | H37: 16 | I37: Shelly PM-4-1.3
B38: P1-120-4 (120V) | E38: 16 | F38: 120V Circuit | H38: 16 | I38: Shelly PM-4-1.4
B39: P1-120-5 (120V) | E39: 16 | F39: 120V Circuit | G39: 40 A GFCI | H39: 16 | I39: Shelly PM-4-2.1
B40: P1-120-6 (120V) | H40: 16 | I40: Shelly PM-4-2.2
B41: P1-120-7 (120V) | H41: 16 | I41: Shelly PM-4-2.3
B42: P1-120-8 (120V) | H42: 16 | I42: Shelly PM-4-2.4
B43: P1-120-9 (120V) | G43: 15 | H43: 15 | I43: Shelly 1 PM
A44: Circuit 13 | B44: 220-1 (220V) | E44: 16 | F44: 220V Circuit | G44: 40 A GFCI | H44: 16 | I44: Shelly PM-4-3.1
B45: 220-2 (220V) | E45: 16 | F45: 220V Circuit | H45: 16 | I45: Shelly PM-4-3.2
B46: 220-3 (220V) | E46: 16 | F46: 220V Circuit | H46: 16 | I46: Shelly PM-4-3.3
B47: 220-4 (220V) | E47: 16 | F47: 220V Circuit | H47: 16 | I47: Shelly PM-4-3.4
A48: Circuit 14 | B48: 220-5 (220V) | E48: 16 | F48: 220V Circuit | G48: 15A | H48: 16 | I48: Shelly 1 PM
A49: Circuit 15 | B49: 220-6 (220V) | E49: 30 | F49: 220V Circuit | G49: 30 A | H49: 30
A50: Circuit 16 | B50: 220-7 (220V) | E50: 40 | F50: 220V Circuit | G50: 40 A | H50: 40
A51: Blinds
A52: Circuit 3 | B52: Lower West 1 | D52: 57.6 | E52: =D52/120 -> 0.48 | F52: 120V Circuit | H52: =sum(E52:E53) -> 1.44 | I52: Shelly Dual Cover 1.1
B53: Lower West 2 | D53: 115.2 | E53: =D53/120 -> 0.96 | F53: Combined 120V-3 | I53: Shelly Dual Cover 1.2
A55: **TOTAL PANEL 2 LOAD** | D55: =sum(D57:D92) -> 4071.02 | E55: =sum(E57:E74) -> 161.22583 | F55: Total | H55: =sum(H57:H74) -> 176.54667
A56: Lighting Loads | B56: Load | C56: Feet/Location | D56: Watts | E56: Continuous A | F56: Transformer | G56: Breaker | H56: NCL A
A57: Total | D57: =sum(D58:D93) -> 2035.51 | E57: =sum(E58:E74) -> 80.612917 | H57: =sum(H58:H74) -> 88.273333
A58: Circuit 1 | B58: P2-EXT1 | C58: 20 | D58: 91.35 | E58: =D58/24 -> 3.80625 | F58: HDR-240-24 (10A) | G58: 5A | H58: 3.81 | I58: ShellY RGBWW Pro | J58: Dimmer
B59: P2-EXT2 | C59: 35 | D59: 159.86 | E59: =D59/24 -> 6.6608333 | F59: HDR-240-24 (10A) | G59: 8A | H59: 6.66 | I59: ShellY RGBWW Pro | J59: Dimmer
A60: Circuit 2 | B60: P2-EXT3 | C60: 16 | D60: 73.08 | E60: =D60/24 -> 3.045 | F60: HDR-240-24 (10A) | G60: 5A | H60: 3.04 | I60: ShellY RGBWW Pro | J60: Dimmer
B61: P2-EXT4 | C61: 40 | D61: 182.7 | E61: =D61/24 -> 7.6125 | F61: HDR-240-24 (10A) | G61: 10A | H61: 7.61 | I61: ShellY RGBWW Pro | J61: Dimmer
A62: Circuit 3 | B62: P2-EXT5 | C62: 70 | D62: 319.72 | E62: =D62/24 -> 13.321667 | F62: HDR-320-24 (13.3A) | G62: 15 A | H62: 13.32 | I62: ShellY RGBWW Pro | J62: Dimmer
A63: Circuit 4 | B63: P2-LVC-1 | D63: 216 | E63: =D63/24 -> 9 | F63: HDR-320-24 (13.3A) | G63: 12A | H63: 9 | I63: ShellY RGBWW Pro | J63: Dimmer
A64: Circuit 5 | B64: P2-LVC-2 | D64: 240 | E64: =D64/24 -> 10 | F64: HDR-320-24 (13.3A) | G64: 15 A | H64: 10 | I64: ShellY RGBWW Pro | J64: Dimmer
A65: Circuit 6 | B65: P2-LVC-3 | D65: 240 | E65: =D65/24 -> 10 | F65: HDR-320-24 (13.3A) | G65: 16 A | H65: 10 | I65: ShellY RGBWW Pro | J65: Dimmer
A66: Circuit 7 | B66: P2-LVM-1 | C66: Mechanical | D66: 18 | E66: =D66/24 -> 0.75 | F66: HDR-480-24 (20A) | G66: 40 | H66: =sum(E66:E74) -> 17.166667 | I66: Shelly PM-4-1.1
B67: P2-LVM-2 | C67: Closet | D67: 48 | E67: =D67/24 -> 2 | F67: Combined 24V-7 | I67: Shelly PM-4-1.2
B68: P2-LVM-4 | C68: Garage | D68: 36 | E68: =D68/24 -> 1.5 | F68: Combined 24V-7 | I68: Shelly PM-4-1.3
B69: P2-LVM-5 | C69: Garage | D69: 126 | E69: =D69/24 -> 5.25 | F69: Combined 24V-7 | I69: Shelly PM-4-1.4
A70: Circuit 8 | B70: P2-LVM-3 | C70: Bath | D70: 72 | E70: =D70/24 -> 3 | F70: HDR-150-24 | G70: 10A | H70: =sum(E70:E74) -> 7.6666667 | I70: Shelly 2 PM Pro-1.1 | J70: Dimmer | M70: 72 | N70: =M70/24 -> 3 | O70: Combined 24V-7
B71: P2-FL-120-1 | D71: 40 | E71: =D71/24 -> 1.6666667 | F71: 120V Circuit | I71: Shelly 2 PM Pro-1.1 | J71: Dimmer
B72: P2-F-120-1 | E72: 1 | F72: 120V Circuit | I72: Shelly PM-1
B73: P2-FL-120-2 | E73: 1 | F73: 120V Circuit | I73: Shelly 2 PM Pro-1.1 | J73: Dimmer
B74: P2-F-120-2 | E74: 1 | F74: 120V Circuit | I74: Shelly PM-1
A75: Wall Loads
E76: =sum(E78:E95) -> 315.4 | H76: =sum(H78:H95) -> 183.44
B77: P1-120-1 | E77: 20 | F77: 120V Circuit | I77: Shelly PM-4-2.4
A78: Circuit 8 | B78: P1-120-2 | E78: 20 | F78: 120V Circuit | G78: 40 A GFCI | H78: 16 | I78: Shelly PM-4-3.1
B79: P1-120-3 | E79: 20 | F79: 120V Circuit | H79: 16 | I79: Shelly PM-4-3.2
B80: P1-120-4 | E80: 20 | F80: 120V Circuit | H80: 16 | I80: Shelly PM-4-3.3
B81: P1-120-5 | E81: 20 | F81: 120V Circuit | H81: 16 | I81: Shelly PM-4-3.4
A82: Circuit 9 | B82: P1-120-6 | E82: 20 | F82: 120V Circuit | G82: 15 | H82: 16 | I82: Shelly PM-1
B83: 220-1 (220V) | E83: 20 | F83: 220V Circuit | G83: 40A | H83: 16 | I83: Shelly PM-4 4.1
B84: 220-2 (220V) | E84: 20 | F84: 220V Circuit | H84: 16 | I84: Shelly PM-4 4.2
A85: Circuit 10 | B85: 220-3 (220V) | E85: 20 | F85: 220V Circuit | I85: Shelly PM-4 4.3
I86: Shelly PM-4 4.4
A87: Circuit 11 | B87: 220-4 (220V) | E87: 30 | F87: 220V Circuit | G87: 30A | H87: 30
A88: Circuit 12 | B88: 220-4 (220V) | E88: 40 | F88: 220V Circuit | G88: 40A | H88: 40
A89: Blinds
A90: Circuit 4 | B90: Glass East | D90: 57.6 | E90: =D90/120 -> 0.48 | F90: 120V Circuit | H90: =sum(E90:E91) -> 0.96 | I90: Shelly Dual Cover 1.1
B91: West Glass 2-1 | D91: 57.6 | E91: =D91/120 -> 0.48 | F91: 120V Circuit | I91: Shelly Dual Cover 1.2
B92: West Glass 2-2 | D92: 57.6 | E92: =D92/120 -> 0.48 | F92: 120V Circuit | H92: =sum(E92) -> 0.48 | I92: Shelly Dual Cover 2.1
A94: **TOTAL PANEL 3 LOAD** | D94: 24V | E94: 83.96 | F94: Total | G94: 179
A95: Lighting Loads | B95: Circuit | C95: Feet | D95: Watts | E95: Amps | F95: Recommended Transformer | G95: Breaker
D96: =sum(D97:D130) -> 2747.36 | E96: =sum(E97:E130) -> 198.87333 | H96: =sum(H97:H117) -> 93.748333
A97: Circuit 1 | B97: P3-EXT-1 | C97: 35 | D97: 160.01 | E97: =D97/24 -> 6.6670833 | F97: HDR-240-24 (10A) | G97: 10A | H97: =E97 -> 6.6670833 | I97: ShellY RGBWW Pro | J97: Dimmer
A98: Circuit 2 | B98: P3-EXT-2 | C98: 15 | D98: 68.58 | E98: =D98/24 -> 2.8575 | F98: HDR-240-24 (10A) | G98: 3.6 A | H98: =E98 -> 2.8575 | I98: ShellY RGBWW Pro | J98: Dimmer
A99: Circuit 3 | B99: P3-EXT-3 | C99: 45 | D99: 205.73 | E99: =D99/24 -> 8.5720833 | F99: HDR-240-24 (10A) | G99: 10.7 A | H99: =E99 -> 8.5720833 | I99: ShellY RGBWW Pro | J99: Dimmer
A100: Circuit 4 | B100: P3-EXT-4 | C100: 65 | D100: 297.17 | E100: =D100/24 -> 12.382083 | F100: HDR-320-24 (13.3A) | G100: 15.5 A | H100: =E100 -> 12.382083 | I100: ShellY RGBWW Pro | J100: Dimmer
A101: Circuit 5 | B101: P3-EXT-5 | C101: 40 | D101: 182.87 | E101: =D101/24 -> 7.6195833 | F101: HDR-240-24 (10A) | G101: 9.5 A | H101: =E101 -> 7.6195833 | I101: ShellY RGBWW Pro | J101: Dimmer
A102: Circuit 6 | B102: P3-LVC-1 | C102: Living | D102: 360 | E102: =D102/24 -> 15 | F102: HDR-480-24 (20A) | G102: 20 A | H102: =E102 -> 15 | I102: ShellY RGBWW Pro | J102: Dimmer
A103: Circuit 7 | B103: P3-LVC-2 | C103: Shower | D103: 120 | E103: =D103/24 -> 5 | F103: HDR-240-24 (10A) | G103: 7A | H103: =E103 -> 5 | I103: ShellY RGBWW Pro | J103: Dimmer
A104: Circuit 8 | B104: P3-LVC-3 | C104: Bath | D104: 168 | E104: =D104/24 -> 7 | F104: HDR-320-24 (13.3A) | G104: 10A | H104: =E104 -> 7 | I104: ShellY RGBWW Pro | J104: Dimmer
A105: Circuit 9 | B105: P3-LVC-4 | C105: Master | D105: 312 | E105: =D105/24 -> 13 | F105: HDR-480-24 (20A) | G105: 15 A | H105: =E105 -> 13 | I105: ShellY RGBWW Pro | J105: Dimmer
...

Sheet Schedule
A1: RAC Development | B1: Craig Engel RAC Inc. | C1: 724 S. 1220 W. Hurricane UT
A2: Tammy Engel | B2: racinc19@gmail.com | C2: Permit # PREP 23-440 | D2: Permit
A3: 1267 N 1390 W St. George UT | B3: 435-229-7360 | C3: Plans | D3: Plans
A4: racinc19billing@gmail.com | C4: Engineering | D4: Engineering
A5: 435-229-4759 | C5: Inspection | D5: Inspection Docs
C6: Selections | D6: Selections
A7: Trade | C7: Progress | E7: Start | F7: Days | G7: Finish | H7: Delay | I7: Notes
A8: -Duration | C8: =AVERAGE(C9:C135) -> 0.94104134 | D8: =IFERROR(__xludf.DUMMYFUNCTION("SPARKLINE(C8,{""charttype"",""bar"";""max"",1})"),"") | E8: =min(E9:E135) -> 45292 | F8: =G8-E8 -> 235 | G8: =MAX(G9:G135) -> 45527 | H8: =sum(H9:H138) -> 128
A9: Pre Construction | C9: =AVERAGE(C10:C16) -> 1 | D9: =IFERROR(__xludf.DUMMYFUNCTION("SPARKLINE(C9,{""charttype"",""bar"";""max"",1})"),"") | E9: =min(E10:E16) -> 45292 | F9: =G9-E9 -> 24 | G9: =MAX(G10:G16) -> 45316 | H9: =SUM(H10:H19) -> 0
A10: Construction Documents | C10: 1 | D10: =IFERROR(__xludf.DUMMYFUNCTION("SPARKLINE(C10,{""charttype"",""bar"";""max"",1})"),"") | E10: 45292 | F10: 1 | G10: =if(F10=0,G9, workday(E10,F10-1))+WORKDAY(H10,H9) -> 45292
A11: Manual J | C11: 1 | D11: =IFERROR(__xludf.DUMMYFUNCTION("SPARKLINE(C11,{""charttype"",""bar"";""max"",1})"),"") | E11: 45293 | F11: 0 | G11: =if(F11=0,G10, workday(E11,F11-1))+WORKDAY(H11,H10) -> 45292
A12: Selection File | C12: 1 | D12: =IFERROR(__xludf.DUMMYFUNCTION("SPARKLINE(C12,{""charttype"",""bar"";""max"",1})"),"") | E12: 45294 | F12: 0 | G12: =if(F12=0,G11, workday(E12,F12-1))+WORKDAY(H12,H11) -> 45292
A13: Schedule File | C13: 1 | D13: =IFERROR(__xludf.DUMMYFUNCTION("SPARKLINE(C13,{""charttype"",""bar"";""max"",1})"),"") | E13: 45295 | F13: 0 | G13: =if(F13=0,G12, workday(E13,F13-1))+WORKDAY(H13,H12) -> 45292
A14: Civial Engineering | C14: 1 | D14: =IFERROR(__xludf.DUMMYFUNCTION("SPARKLINE(C14,{""charttype"",""bar"";""max"",1})"),"") | E14: 45296 | F14: 1 | G14: =if(F14=0,G13, workday(E14,F14-1))+WORKDAY(H14,H13) -> 45296
A15: Structural Engineering | C15: 1 | D15: =IFERROR(__xludf.DUMMYFUNCTION("SPARKLINE(C15,{""charttype"",""bar"";""max"",1})"),"") | E15: 45297 | F15: 1 | G15: =if(F15=0,G14, workday(E15,F15-1))+WORKDAY(H15,H14) -> 45297
A16: Permit | C16: 1 | D16: =IFERROR(__xludf.DUMMYFUNCTION("SPARKLINE(C16,{""charttype"",""bar"";""max"",1})"),"") | E16: 45298 | F16: 15 | G16: =if(F16=0,G15, workday(E16,F16-1))+WORKDAY(H16,H15) -> 45316
A17: Material Deposits | C17: 1 | D17: =IFERROR(__xludf.DUMMYFUNCTION("SPARKLINE(C17,{""charttype"",""bar"";""max"",1})"),"") | E17: 45299 | F17: 15 | G17: =if(F17=0,G16, workday(E17,F17-1))+WORKDAY(H17,H16) -> 45317
A18: Temp Power | B18: I Tech Electric | C18: 1 | D18: =IFERROR(__xludf.DUMMYFUNCTION("SPARKLINE(C18,{""charttype"",""bar"";""max"",1})"),"") | E18: 45299 | F18: 1 | G18: =if(F18=0,G16, workday(E18,F18-1))+WORKDAY(H18,H16) -> 45299
A19: Job Sign | C19: 1 | D19: =IFERROR(__xludf.DUMMYFUNCTION("SPARKLINE(C19,{""charttype"",""bar"";""max"",1})"),"") | E19: 45355 | F19: 0 | G19: =if(F19=0,G18, workday(E19,F19-1))+WORKDAY(H19,H18) -> 45299
A20: Site Prep | C20: =average(C21:C26) -> 1 | D20: =IFERROR(__xludf.DUMMYFUNCTION("SPARKLINE(C20,{""charttype"",""bar"";""max"",1})"),"") | E20: =min(E21:E26) -> 45317 | F20: =G20-E20 -> 10 | G20: =MAX(G21:G26) -> 45327 | H20: =sum(H21:H26) -> 0
A21: Survey | C21: 1 | D21: =IFERROR(__xludf.DUMMYFUNCTION("SPARKLINE(C21,{""charttype"",""bar"";""max"",1})"),"") | E21: =workday(G16,1) -> 45317 | F21: 1 | G21: =if(F21=0,G20, workday(E21,F21-1))+WORKDAY(H21,H20) -> 45317
A22: Site Walls | C22: 1 | D22: =IFERROR(__xludf.DUMMYFUNCTION("SPARKLINE(C22,{""charttype"",""bar"";""max"",1})"),"") | E22: =workday(G21,1) -> 45320 | F22: 5 | G22: =if(F22=0,G21, workday(E22,F22-1))+WORKDAY(H22,H21) -> 45324
A23: Dumpster | C23: 1 | D23: =IFERROR(__xludf.DUMMYFUNCTION("SPARKLINE(C23,{""charttype"",""bar"";""max"",1})"),"") | E23: =workday(G22,1) -> 45327 | F23: 1 | G23: =if(F23=0,G22, workday(E23,F23-1))+WORKDAY(H23,H22) -> 45327
A24: Portable Toilet | C24: 1 | D24: =IFERROR(__xludf.DUMMYFUNCTION("SPARKLINE(C24,{""charttype"",""bar"";""max"",1})"),"") | E24: =workday(G23,1) -> 45328 | F24: 0 | G24: =if(F24=0,G23, workday(E24,F24-1))+WORKDAY(H24,H23) -> 45327
A25: Temp Water | C25: 1 | D25: =IFERROR(__xludf.DUMMYFUNCTION("SPARKLINE(C25,{""charttype"",""bar"";""max"",1})"),"") | E25: =workday(G24,1) -> 45328 | F25: 0 | G25: =if(F25=0,G24, workday(E25,F25-1))+WORKDAY(H25,H24) -> 45327
A26: Temp Electric Meter | C26: 1 | D26: =IFERROR(__xludf.DUMMYFUNCTION("SPARKLINE(C26,{""charttype"",""bar"";""max"",1})"),"") | E26: =workday(G25,1) -> 45328 | F26: 0 | G26: =if(F26=0,G25, workday(E26,F26-1))+WORKDAY(H26,H25) -> 45327
A27: Foundation | C27: =average(C28:C46) -> 1 | D27: =IFERROR(__xludf.DUMMYFUNCTION("SPARKLINE(C27,{""charttype"",""bar"";""max"",1})"),"") | E27: =min(E28:E46) -> 45292 | F27: =G27-E27 -> 78 | G27: =MAX(G28:G46) -> 45370 | H27: =sum(H28:H46) -> 42
A28: Strings | B28: RG QUALITY CONCRETE | C28: 1 | D28: =IFERROR(__xludf.DUMMYFUNCTION("SPARKLINE(C28,{""charttype"",""bar"";""max"",1})"),"") | E28: 45292 | F28: 1 | G28: =if(F28=0,E28, workday(E28,F28-1)) -> 45292
A29: Footing Dig | C29: 1 | D29: =IFERROR(__xludf.DUMMYFUNCTION("SPARKLINE(C29,{""charttype"",""bar"";""max"",1})"),"") | E29: =if(F29=0,E28,if(H28=0,workday(G28,1),workday(G28,H28))) -> 45293 | F29: 1 | G29: =if(F29=0,E29, workday(E29,F29-1)) -> 45293
A30: Place Pea Gravel | C30: 1 | D30: =IFERROR(__xludf.DUMMYFUNCTION("SPARKLINE(C30,{""charttype"",""bar"";""max"",1})"),"") | E30: =if(F30=0,E29,if(H29=0,workday(G29,1),workday(G29,H29))) -> 45294 | F30: 1 | G30: =if(F30=0,E30, workday(E30,F30-1)) -> 45294
A31: Footing Compaction Inspect | C31: 1 | D31: =IFERROR(__xludf.DUMMYFUNCTION("SPARKLINE(C31,{""charttype"",""bar"";""max"",1})"),"") | E31: =if(F31=0,E30,if(H30=0,workday(G30,1),workday(G30,H30))) -> 45295 | F31: 1 | G31: =if(F31=0,E31, workday(E31,F31-1)) -> 45295
A32: Setting Forms | C32: 1 | D32: =IFERROR(__xludf.DUMMYFUNCTION("SPARKLINE(C32,{""charttype"",""bar"";""max"",1})"),"") | E32: =if(F32=0,E31,if(H31=0,workday(G31,1),workday(G31,H31))) -> 45296 | F32: 1 | G32: =if(F32=0,E32, workday(E32,F32-1)) -> 45296
A33: Setting Rebar/Blockouts | C33: 1 | D33: =IFERROR(__xludf.DUMMYFUNCTION("SPARKLINE(C33,{""charttype"",""bar"";""max"",1})"),"") | E33: =if(F33=0,E32,if(H32=0,workday(G32,1),workday(G32,H32))) -> 45299 | F33: 1 | G33: =if(F33=0,E33, workday(E33,F33-1)) -> 45299 | H33: 40
A34: Underground Plumbing | B34: MASTER PLUMBING SYSTEMS | C34: 1 | D34: =IFERROR(__xludf.DUMMYFUNCTION("SPARKLINE(C34,{""charttype"",""bar"";""max"",1})"),"") | E34: =if(F34=0,E33,if(H33=0,workday(G33,1),workday(G33,H33))) -> 45355 | F34: 2 | G34: =if(F34=0,E34, workday(E34,F34-1)) -> 45356
A35: Plumbing Inspect | C35: 1 | D35: =IFERROR(__xludf.DUMMYFUNCTION("SPARKLINE(C35,{""charttype"",""bar"";""max"",1})"),"") | E35: =if(F35=0,E34,if(H34=0,workday(G34,1),workday(G34,H34))) -> 45357 | F35: 1 | G35: =if(F35=0,E35, workday(E35,F35-1)) -> 45357
A36: Pour Footings | C36: 1 | D36: =IFERROR(__xludf.DUMMYFUNCTION("SPARKLINE(C36,{""charttype"",""bar"";""max"",1})"),"") | E36: =if(F36=0,E35,if(H35=0,workday(G35,1),workday(G35,H35))) -> 45358 | F36: 1 | G36: =if(F36=0,E36, workday(E36,F36-1)) -> 45358
A37: Shade and fill | B37: RG QUALITY CONCRETE | C37: 1 | D37: =IFERROR(__xludf.DUMMYFUNCTION("SPARKLINE(C37,{""charttype"",""bar"";""max"",1})"),"") | E37: =if(F37=0,E36,if(H36=0,workday(G36,1),workday(G36,H36))) -> 45359 | F37: 1 | G37: =if(F37=0,E37, workday(E37,F37-1)) -> 45359
A38: Underground Electric | C38: 1 | D38: =IFERROR(__xludf.DUMMYFUNCTION("SPARKLINE(C38,{""charttype"",""bar"";""max"",1})"),"") | E38: =if(F38=0,E37,if(H37=0,workday(G37,1),workday(G37,H37))) -> 45362 | F38: 1 | G38: =if(F38=0,E38, workday(E38,F38-1)) -> 45362
A39: Termite | C39: 1 | D39: =IFERROR(__xludf.DUMMYFUNCTION("SPARKLINE(C39,{""charttype"",""bar"";""max"",1})"),"") | E39: =if(F39=0,E38,if(H38=0,workday(G38,1),workday(G38,H38))) -> 45362 | F39: 0 | G39: =if(F39=0,E39, workday(E39,F39-1)) -> 45362
A40: Slab inspection | C40: 1 | D40: =IFERROR(__xludf.DUMMYFUNCTION("SPARKLINE(C40,{""charttype"",""bar"";""max"",1})"),"") | E40: =if(F40=0,E39,if(H39=0,workday(G39,1),workday(G39,H39))) -> 45363 | F40: 1 | G40: =if(F40=0,E40, workday(E40,F40-1)) -> 45363
A41: Place Gravel/Int Footing | C41: 1 | D41: =IFERROR(__xludf.DUMMYFUNCTION("SPARKLINE(C41,{""charttype"",""bar"";""max"",1})"),"") | E41: =if(F41=0,E40,if(H40=0,workday(G40,1),workday(G40,H40))) -> 45364 | F41: 1 | G41: =if(F41=0,E41, workday(E41,F41-1)) -> 45364 | H41: 2
A42: Place & tape Vapor | C42: 1 | D42: =IFERROR(__xludf.DUMMYFUNCTION("SPARKLINE(C42,{""charttype"",""bar"";""max"",1})"),"") | E42: =if(F42=0,E41,if(H41=0,workday(G41,1),workday(G41,H41))) -> 45366 | F42: 1 | G42: =if(F42=0,E42, workday(E42,F42-1)) -> 45366
A43: Form Recess | C43: 1 | D43: =IFERROR(__xludf.DUMMYFUNCTION("SPARKLINE(C43,{""charttype"",""bar"";""max"",1})"),"") | E43: =if(F43=0,E42,if(H42=0,workday(G42,1),workday(G42,H42))) -> 45366 | F43: 0 | G43: =if(F43=0,E43, workday(E43,F43-1)) -> 45366
A44: Slab Pour | C44: 1 | D44: =IFERROR(__xludf.DUMMYFUNCTION("SPARKLINE(C44,{""charttype"",""bar"";""max"",1})"),"") | E44: =if(F44=0,E43,if(H43=0,workday(G43,1),workday(G43,H43))) -> 45369 | F44: 1 | G44: =if(F44=0,E44, workday(E44,F44-1)) -> 45369
A45: Garage/Recess Pour | C45: 1 | D45: =IFERROR(__xludf.DUMMYFUNCTION("SPARKLINE(C45,{""charttype"",""bar"";""max"",1})"),"") | E45: =if(F45=0,E44,if(H44=0,workday(G44,1),workday(G44,H44))) -> 45370 | F45: 1 | G45: =if(F45=0,E45, workday(E45,F45-1)) -> 45370
A46: Strip and Close and grade | C46: 1 | D46: =IFERROR(__xludf.DUMMYFUNCTION("SPARKLINE(C46,{""charttype"",""bar"";""max"",1})"),"") | E46: =if(F46=0,E45,if(H45=0,workday(G45,1),workday(G45,H45))) -> 45370 | F46: 0 | G46: =if(F46=0,E46, workday(E46,F46-1)) -> 45370
A47: Structure | C47: =Average(C48:C59) -> 1 | D47: =IFERROR(__xludf.DUMMYFUNCTION("SPARKLINE(C47,{""charttype"",""bar"";""max"",1})"),"") | E47: =min(E48:E59) -> 45371 | F47: =G47-E47 -> 12 | G47: =MAX(G48:G59) -> 45383 | H47: =sum(H48:H59) -> 0
A48: Notify Verify Truss | B48: St. George Truss | C48: 1 | D48: =IFERROR(__xludf.DUMMYFUNCTION("SPARKLINE(C48,{""charttype"",""bar"";""max"",1})"),"") | E48: =workday(G46,1) -> 45371 | F48: 1 | G48: =if(F48=0,G47, workday(E48,F48-1))+WORKDAY(H48,H47) -> 45371
A49: Deliver Wall Lumber | B49: Sunpro | C49: 1 | D49: =IFERROR(__xludf.DUMMYFUNCTION("SPARKLINE(C49,{""charttype"",""bar"";""max"",1})"),"") | E49: =if(F49=0,E48,if(H48=0,workday(G48,1),workday(G48,H48))) -> 45371 | F49: 0 | G49: =if(F49=0,G48, workday(E49,F49-1))+WORKDAY(H49,H48) -> 45371
A50: Notify Gas Utilities | C50: 1 | D50: =IFERROR(__xludf.DUMMYFUNCTION("SPARKLINE(C50,{""charttype"",""bar"";""max"",1})"),"") | E50: =if(F50=0,E49,if(H49=0,workday(G49,1),workday(G49,H49))) -> 45371 | F50: 0 | G50: =if(F50=0,G49, workday(E50,F50-1))+WORKDAY(H50,H49) -> 45371
A51: Wall Framing | C51: 1 | D51: =IFERROR(__xludf.DUMMYFUNCTION("SPARKLINE(C51,{""charttype"",""bar"";""max"",1})"),"") | E51: =if(F51=0,E50,if(H50=0,workday(G50,1),workday(G50,H50))) -> 45372 | F51: 2 | G51: =if(F51=0,G50, workday(E51,F51-1))+WORKDAY(H51,H50) -> 45373
A52: Deliver Truss/Roof Wood | B52: St. George Truss | C52: 1 | D52: =IFERROR(__xludf.DUMMYFUNCTION("SPARKLINE(C52,{""charttype"",""bar"";""max"",1})"),"") | E52: =if(F52=0,E51,if(H51=0,workday(G51,1),workday(G51,H51))) -> 45376 | F52: 1 | G52: =if(F52=0,G51, workday(E52,F52-1))+WORKDAY(H52,H51) -> 45376
A53: Roof Framing | C53: 1 | D53: =IFERROR(__xludf.DUMMYFUNCTION("SPARKLINE(C53,{""charttype"",""bar"";""max"",1})"),"") | E53: =if(F53=0,E52,if(H52=0,workday(G52,1),workday(G52,H52))) -> 45377 | F53: 2 | G53: =if(F53=0,G52, workday(E53,F53-1))+WORKDAY(H53,H52) -> 45378
A54: Deliver Punch Wood | C54: 1 | D54: =IFERROR(__xludf.DUMMYFUNCTION("SPARKLINE(C54,{""charttype"",""bar"";""max"",1})"),"") | E54: =if(F54=0,E53,if(H53=0,workday(G53,1),workday(G53,H53))) -> 45379 | F54: 1 | G54: =if(F54=0,G53, workday(E54,F54-1))+WORKDAY(H54,H53) -> 45379
A55: Framing Punch | C55: 1 | D55: =IFERROR(__xludf.DUMMYFUNCTION("SPARKLINE(C55,{""charttype"",""bar"";""max"",1})"),"") | E55: =if(F55=0,E54,if(H54=0,workday(G54,1),workday(G54,H54))) -> 45380 | F55: 2 | G55: =if(F55=0,G54, workday(E55,F55-1))+WORKDAY(H55,H54) -> 45383
A56: Deliver Drains & Piping | B56: MASTER PLUMBING SYSTEMS | C56: 1 | D56: =IFERROR(__xludf.DUMMYFUNCTION("SPARKLINE(C56,{""charttype"",""bar"";""max"",1})"),"") | E56: =if(F56=0,E55,if(H55=0,workday(G55,1),workday(G55,H55))) -> 45380 | F56: 0 | G56: =if(F56=0,G55, workday(E56,F56-1))+WORKDAY(H56,H55) -> 45383
A57: Roof Drains | B57: MASTER PLUMBING SYSTEMS | C57: 1 | D57: =IFERROR(__xludf.DUMMYFUNCTION("SPARKLINE(C57,{""charttype"",""bar"";""max"",1})"),"") | E57: =if(F57=0,E56,if(H56=0,workday(G56,1),workday(G56,H56))) -> 45380 | F57: 0 | G57: =if(F57=0,G56, workday(E57,F57-1))+WORKDAY(H57,H56) -> 45383
A58: Electrical Main | B58: I Tech Electric | C58: 1 | D58: =IFERROR(__xludf.DUMMYFUNCTION("SPARKLINE(C58,{""charttype"",""bar"";""max"",1})"),"") | E58: =if(F58=0,E57,if(H57=0,workday(G57,1),workday(G57,H57))) -> 45380 | F58: 0 | G58: =if(F58=0,G57, workday(E58,F58-1))+WORKDAY(H58,H57) -> 45383
A59: Gas Stub | C59: 1 | D59: =IFERROR(__xludf.DUMMYFUNCTION("SPARKLINE(C59,{""charttype"",""bar"";""max"",1})"),"") | E59: =if(F59=0,E58,if(H58=0,workday(G58,1),workday(G58,H58))) -> 45380 | F59: 0 | G59: =if(F59=0,G58, workday(E59,F59-1))+WORKDAY(H59,H58) -> 45383
A60: Dry in | C60: =Average(C61:C66) -> 1 | D60: =IFERROR(__xludf.DUMMYFUNCTION("SPARKLINE(C60,{""charttype"",""bar"";""max"",1})"),"") | E60: =min(E61:E66) -> 45380 | F60: =G60-E60 -> 4 | G60: =MAX(G61:G66) -> 45384 | H60: =sum(H61:H66) -> 0
A61: Roofing IWS | B61: Pierce Siding | C61: 1 | D61: =IFERROR(__xludf.DUMMYFUNCTION("SPARKLINE(C61,{""charttype"",""bar"";""max"",1})"),"") | E61: =if(F61=0,E54,if(H54=0,workday(G54,1),workday(G54,H54))) -> 45380 | F61: 1 | G61: =if(F61=0,G60, workday(E61,F61-1))+WORKDAY(H61,H60) -> 45380
A62: Deliver Exterior Doors | B62: Sunpro | C62: 1 | D62: =IFERROR(__xludf.DUMMYFUNCTION("SPARKLINE(C62,{""charttype"",""bar"";""max"",1})"),"") | E62: =workday(G56,1) -> 45384 | F62: 1 | G62: =if(F62=0,E62, workday(E62,F62-1)) -> 45384
A63: Install Exterior Doors | B63: Estimate# 3561 MVE Lot 6.pdf | C63: 1 | D63: =IFERROR(__xludf.DUMMYFUNCTION("SPARKLINE(C63,{""charttype"",""bar"";""max"",1})"),"") | E63: =if(F63=0,E62,if(H62=0,workday(G62,1),workday(G62,H62))) -> 45384 | F63: 0 | G63: =if(F63=0,E63, workday(E63,F63-1)) -> 45384
A64: Deliver Windows | B64: LP Building Solutions | C64: 1 | D64: =IFERROR(__xludf.DUMMYFUNCTION("SPARKLINE(C64,{""charttype"",""bar"";""max"",1})"),"") | E64: =if(F64=0,E63,if(H63=0,workday(G63,1),workday(G63,H63))) -> 45384 | F64: 0 | G64: =if(F64=0,E64, workday(E64,F64-1)) -> 45384
A65: Install Exterior Glass | B65: LP Building Solutions | C65: 1 | D65: =IFERROR(__xludf.DUMMYFUNCTION("SPARKLINE(C65,{""charttype"",""bar"";""max"",1})"),"") | E65: =if(F65=0,E64,if(H64=0,workday(G64,1),workday(G64,H64))) -> 45384 | F65: 0 | G65: =if(F65=0,E65, workday(E65,F65-1)) -> 45384
A66: Deliver/Install Entry Doors | B66: URBAN DOORS | C66: 1 | D66: =IFERROR(__xludf.DUMMYFUNCTION("SPARKLINE(C66,{""charttype"",""bar"";""max"",1})"),"") | E66: =if(F66=0,E65,if(H65=0,workday(G65,1),workday(G65,H65))) -> 45384 | F66: 0 | G66: =if(F66=0,E66, workday(E66,F66-1)) -> 45384
A67: Rough/5Way | C67: =Average(C68:C73) -> 1 | D67: =IFERROR(__xludf.DUMMYFUNCTION("SPARKLINE(C67,{""charttype"",""bar"";""max"",1})"),"") | E67: =min(E68:E73) -> 45384 | F67: =G67-E67 -> 20 | G67: =MAX(G68:G73) -> 45404 | H67: =sum(H68:H73) -> 2
A68: Rough Mechanical | B68: KUHNS HEATING & AIR | C68: 1 | D68: =IFERROR(__xludf.DUMMYFUNCTION("SPARKLINE(C68,{""charttype"",""bar"";""max"",1})"),"") | E68: =workday(G56,1) -> 45384 | F68: 2 | G68: =if(F68=0,G67, workday(E68,F68-1))+WORKDAY(H68,H67) -> 45388 | H68: 1
A69: Rough Plumbing/Gas/Roof Drains | B69: MASTER PLUMBING SYSTEMS | C69: 1 | D69: =IFERROR(__xludf.DUMMYFUNCTION("SPARKLINE(C69,{""charttype"",""bar"";""max"",1})"),"") | E69: =if(F69=0,E68,if(H68=0,workday(G68,1),workday(G68,H68))) -> 45390 | F69: 2 | G69: =if(F69=0,G68, workday(E69,F69-1))+WORKDAY(H69,H68) -> 45393 | H69: 1
A70: Rough Electrical | B70: I Tech Electric | C70: 1 | D70: =IFERROR(__xludf.DUMMYFUNCTION("SPARKLINE(C70,{""charttype"",""bar"";""max"",1})"),"") | E70: =if(F70=0,E69,if(H69=0,workday(G69,1),workday(G69,H69))) -> 45394 | F70: 3 | G70: =if(F70=0,G69, workday(E70,F70-1))+WORKDAY(H70,H69) -> 45400 | H70: 0
A71: Rough Gas | C71: 1 | D71: =IFERROR(__xludf.DUMMYFUNCTION("SPARKLINE(C71,{""charttype"",""bar"";""max"",1})"),"") | E71: =if(F71=0,E70,if(H70=0,workday(G70,1),workday(G70,H70))) -> 45401 | F71: 1 | G71: =if(F71=0,G70, workday(E71,F71-1))+WORKDAY(H71,H70) -> 45401
A72: 5 Way | C72: 1 | D72: =IFERROR(__xludf.DUMMYFUNCTION("SPARKLINE(C72,{""charttype"",""bar"";""max"",1})"),"") | E72: =if(F72=0,E71,if(H71=0,workday(G71,1),workday(G71,H71))) -> 45404 | F72: 1 | G72: =if(F72=0,G70, workday(E72,F72-1))+WORKDAY(H72,H70) -> 45404
A73: Rough Punch | C73: 1 | D73: =IFERROR(__xludf.DUMMYFUNCTION("SPARKLINE(C73,{""charttype"",""bar"";""max"",1})"),"") | E73: =if(F73=0,E72,if(H72=0,workday(G72,1),workday(G72,H72))) -> 45404 | F73: 0 | G73: =if(F73=0,G72, workday(E73,F73-1))+WORKDAY(H73,H72) -> 45404
A74: Exterior Sealing | C74: =AVERAGE(C75:C87) -> 1 | D74: =IFERROR(__xludf.DUMMYFUNCTION("SPARKLINE(C74,{""charttype"",""bar"";""max"",1})"),"") | E74: =min(E75:E87) -> 45405 | F74: =G74-E74 -> 51 | G74: =MAX(G75:G87) -> 45456 | H74: =sum(H75:H87) -> 9
A75: Set Scaffold | B75: SIPCO/BSM | C75: 1 | D75: =IFERROR(__xludf.DUMMYFUNCTION("SPARKLINE(C75,{""charttype"",""bar"";""max"",1})"),"") | E75: =workday(G73,1) -> 45405 | F75: 1 | G75: =if(F75=1,E75,WORKDAY(E75,(F75+H75))) -> 45405
A76: Hang Exterior Gyp | B76: H&E DRYWALL | C76: 1 | D76: =IFERROR(__xludf.DUMMYFUNCTION("SPARKLINE(C76,{""charttype"",""bar"";""max"",1})"),"") | E76: =if(F76=0,E75,workday(G75,1)) -> 45406 | F76: 1 | G76: =if(F76=1,E76,WORKDAY(E76,(F76+H76))) -> 45406
A77: Lath | B77: SIPCO/BSM | C77: 1 | D77: =IFERROR(__xludf.DUMMYFUNCTION("SPARKLINE(C77,{""charttype"",""bar"";""max"",1})"),"") | E77: =if(F77=0,E76,workday(G76,1)) -> 45406 | F77: 0 | G77: =if(F77=1,E77,WORKDAY(E77,(F77+H77))) -> 45406
A78: Lath Inspection | C78: 1 | D78: =IFERROR(__xludf.DUMMYFUNCTION("SPARKLINE(C78,{""charttype"",""bar"";""max"",1})"),"") | E78: =if(F78=0,E77,workday(G77,1)) -> 45407 | F78: 1 | G78: =if(F78=1,E78,WORKDAY(E78,(F78+H78))) -> 45407
A79: Brown | C79: 1 | D79: =IFERROR(__xludf.DUMMYFUNCTION("SPARKLINE(C79,{""charttype"",""bar"";""max"",1})"),"") | E79: =if(F79=0,E78,workday(G78,1)) -> 45408 | F79: 2 | G79: =if(F79=1,E79,WORKDAY(E79,(F79+H79))) -> 45425 | H79: 9
A80: Color | C80: 1 | D80: =IFERROR(__xludf.DUMMYFUNCTION("SPARKLINE(C80,{""charttype"",""bar"";""max"",1})"),"") | E80: =if(F80=0,E79,workday(G79,1)) -> 45426 | F80: 3 | G80: =if(F80=1,E80,WORKDAY(E80,(F80+H80))) -> 45429
A81: Gas Meter | C81: 1 | D81: =IFERROR(__xludf.DUMMYFUNCTION("SPARKLINE(C81,{""charttype"",""bar"";""max"",1})"),"") | E81: =if(F81=0,E80,workday(G80,1)) -> 45432 | F81: 1 | G81: =if(F81=1,E81,WORKDAY(E81,(F81+H81))) -> 45432
A82: Exterior Stone | C82: 1 | D82: =IFERROR(__xludf.DUMMYFUNCTION("SPARKLINE(C82,{""charttype"",""bar"";""max"",1})"),"") | E82: =if(F82=0,E81,workday(G81,1)) -> 45433 | F82: 3 | G82: =if(F82=1,E82,WORKDAY(E82,(F82+H82))) -> 45436
A83: Cladding Metal | B83: Broken Horn Welding | C83: 1 | D83: =IFERROR(__xludf.DUMMYFUNCTION("SPARKLINE(C83,{""charttype"",""bar"";""max"",1})"),"") | E83: =if(F83=0,E82,workday(G82,1)) -> 45439 | F83: 5 | G83: =if(F83=1,E83,WORKDAY(E83,(F83+H83))) -> 45446
A84: Silicone | C84: 1 | D84: =IFERROR(__xludf.DUMMYFUNCTION("SPARKLINE(C84,{""charttype"",""bar"";""max"",1})"),"") | E84: =if(F84=0,E83,workday(G83,1)) -> 45447 | F84: 2 | G84: =if(F84=1,E84,WORKDAY(E84,(F84+H84))) -> 45449
A85: Roofing Metal | C85: 1 | D85: =IFERROR(__xludf.DUMMYFUNCTION("SPARKLINE(C85,{""charttype"",""bar"";""max"",1})"),"") | E85: =if(F85=0,E84,workday(G84,1)) -> 45450 | F85: 2 | G85: =if(F85=1,E85,WORKDAY(E85,(F85+H85))) -> 45454
A86: Dimple Mat | C86: 1 | D86: =IFERROR(__xludf.DUMMYFUNCTION("SPARKLINE(C86,{""charttype"",""bar"";""max"",1})"),"") | E86: =if(F86=0,E85,workday(G85,1)) -> 45455 | F86: 1 | G86: =if(F86=1,E86,WORKDAY(E86,(F86+H86))) -> 45455
A87: Ballast | C87: 1 | D87: =IFERROR(__xludf.DUMMYFUNCTION("SPARKLINE(C87,{""charttype"",""bar"";""max"",1})"),"") | E87: =if(F87=0,E86,workday(G86,1)) -> 45456 | F87: 1 | G87: =if(F87=1,E87,WORKDAY(E87,(F87+H87))) -> 45456
A88: Insulation Wall Substrate | C88: =AVERAGE(C89:C100) -> 0.9875 | D88: =IFERROR(__xludf.DUMMYFUNCTION("SPARKLINE(C88,{""charttype"",""bar"";""max"",1})"),"") | E88: =min(E89:E100) -> 45405 | F88: =G88-E88 -> 43 | G88: =MAX(G89:G100) -> 45448 | H88: =sum(H89:H100) -> 3
A89: Net & Blow | B89: LP Building Solutions | C89: 1 | D89: =IFERROR(__xludf.DUMMYFUNCTION("SPARKLINE(C89,{""charttype"",""bar"";""max"",1})"),"") | E89: =workday(G72,1) -> 45405 | F89: 2 | G89: =if(F89=1,E89,WORKDAY(E89,(F89))) -> 45407
A90: Insulation Inspection | C90: 1 | D90: =IFERROR(__xludf.DUMMYFUNCTION("SPARKLINE(C90,{""charttype"",""bar"";""max"",1})"),"") | E90: =if(F90=0,E89,workday(G89,1+H90)) -> 45408 | F90: 1 | G90: =if(F90=1,E90,WORKDAY(E90,(F90+H90))) -> 45408
A91: Install Trim | C91: 1 | D91: =IFERROR(__xludf.DUMMYFUNCTION("SPARKLINE(C91,{""charttype"",""bar"";""max"",1})"),"") | E91: =if(F91=0,E90,workday(G90,1)) -> 45411 | F91: 3 | G91: =if(F91=1,E91,WORKDAY(E91,(F91+H91))) -> 45414
A92: Delivery Drywall | B92: H&E DRYWALL | C92: 1 | D92: =IFERROR(__xludf.DUMMYFUNCTION("SPARKLINE(C92,{""charttype"",""bar"";""max"",1})"),"") | E92: =if(F92=0,E91,workday(G91,1)) -> 45415 | F92: 1 | G92: =if(F92=1,E92,WORKDAY(E92,(F92+H92))) -> 45415
A93: Hang | C93: 1 | D93: =IFERROR(__xludf.DUMMYFUNCTION("SPARKLINE(C93,{""charttype"",""bar"";""max"",1})"),"") | E93: =if(F93=0,E92,workday(G92,1)) -> 45418 | F93: 4 | G93: =if(F93=1,E93,WORKDAY(E93,(F93+H93))) -> 45425 | H93: 1
A94: Blower Door | C94: 1 | D94: =IFERROR(__xludf.DUMMYFUNCTION("SPARKLINE(C94,{""charttype"",""bar"";""max"",1})"),"") | E94: =if(F94=0,E93,workday(G93,1)) -> 45418 | F94: 0 | G94: =if(F94=1,E94,WORKDAY(E94,(F94+H94))) -> 45418
A95: Tape & Texture | C95: 1 | D95: =IFERROR(__xludf.DUMMYFUNCTION("SPARKLINE(C95,{""charttype"",""bar"";""max"",1})"),"") | E95: =if(F95=0,E94,workday(G94,1)) -> 45419 | F95: 11 | G95: =if(F95=1,E95,WORKDAY(E95,(F95+H95))) -> 45434
A96: Shelfing | C96: 1 | D96: =IFERROR(__xludf.DUMMYFUNCTION("SPARKLINE(C96,{""charttype"",""bar"";""max"",1})"),"") | E96: =if(F96=0,E95,workday(G95,1)) -> 45435 | F96: 1 | G96: =if(F96=1,E96,WORKDAY(E96,(F96+H96))) -> 45435
A97: Paint | B97: RED HILLS PAINTING | C97: 1 | D97: =IFERROR(__xludf.DUMMYFUNCTION("SPARKLINE(C97,{""charttype"",""bar"";""max"",1})"),"") | E97: =if(F97=0,E96,workday(G96,1+H97)) -> 45440 | F97: 5 | G97: =if(F97=1,E97,WORKDAY(E97,(F97))) -> 45447 | H97: 2
A98: Permanent Power | B98: I Tech Electric | C98: 1 | D98: =IFERROR(__xludf.DUMMYFUNCTION("SPARKLINE(C98,{""charttype"",""bar"";""max"",1})"),"") | E98: =if(F98=0,E97,workday(G97,1+H98)) -> 45440 | F98: 0 | G98: =if(F98=1,E98,WORKDAY(E98,(F98))) -> 45440
A99: Garage Door | B99: LP Building Solutions | C99: 1 | D99: =IFERROR(__xludf.DUMMYFUNCTION("SPARKLINE(C99,{""charttype"",""bar"";""max"",1})"),"") | E99: =if(F99=0,E98,workday(G98,1+H99)) -> 45440 | F99: 0 | G99: =if(F99=1,E99,WORKDAY(E99,(F99))) -> 45440
A100: Set HVAC | B100: KUHNS HEATING & AIR | C100: 0.85 | D100: =IFERROR(__xludf.DUMMYFUNCTION("SPARKLINE(C100,{""charttype"",""bar"";""max"",1})"),"") | E100: =if(F100=0,E99,workday(G99,1+H100)) -> 45441 | F100: 5 | G100: =if(F100=1,E100,WORKDAY(E100,(F100))) -> 45448
...

Sheet Tammy
A1: =Budget1!A1 -> Who is it Yes I meet that bunch of real cast like you know you got to watch you I this guy Got fucking indigestion from the sugar Yep Well yeah I feel like I know I've stabbed you you It's not too long that's just not fair to me Oh Whoops | B1: =Budget1!C3 -> Budget | C1: Date
A2: =Budget1!A2 | D2: Draw 1 | E2: Draw 2 | F2: Draw 3 | G2: Draw 4 | H2: Draw 5 | I2: Draw 6 | J2: Draw 7 | K2: Draw 8 | L2: Draw 9 | M2: Draw 10 | N2: Draw 11 | O2: Draw 12 | P2: Draw 13 | Q2: Draw 14 | R2: Draw 15 | S2: Draw 16 | T2: Draw 17
B3: Budget | C3: Outstanding
B4: =sum(B7:B95) -> 2775448.5 | C4: =sum(D4:T4)-B4 -> -2774723.5 | D4: =sum(D7:D95) -> 725 | E4: =sum(E7:E95) -> 0 | F4: =sum(F7:F95) -> 0 | G4: =sum(G7:G95) -> 0 | H4: =sum(H7:H95) -> 0 | I4: =sum(I7:I95) -> 0 | J4: =sum(J7:J95) -> 0 | K4: =sum(K7:K95) -> 0 | ... T4: =sum(T7:T95) -> 0
A5: =Budget1!A5 | B5: =Budget1!C5
A6: =Budget1!A6 -> Deposit | B6: =Budget1!C6
A7: =Budget1!A7 -> Plumbing Fixtures | B7: =Budget1!C7 -> 17000 | C7: =sum(D7:T7)-B7 -> -17000
A8: =Budget1!A8 -> Electrical Fixtures | B8: =Budget1!C8 -> 18000 | C8: =sum(D8:T8)-B8 -> -18000
A9: =Budget1!A9 -> Hidden Door | B9: =Budget1!C9 -> 25000 | C9: =sum(D9:T9)-B9 -> -25000
A10: =Budget1!A10 -> Vault Door | B10: =Budget1!C10 -> 7500 | C10: =sum(D10:T10)-B10 -> -7500
A11: =Budget1!A11 -> Cabinet | B11: =Budget1!C11 -> 26000 | C11: =sum(D11:T11)-B11 -> -26000
A12: =Budget1!A12 -> Entry Stair | B12: =Budget1!C12 -> 17000 | C12: =sum(D12:T12)-B12 -> -17000
A13: =Budget1!A13 -> Tile Material | B13: =Budget1!C13 -> 80000 | C13: =sum(D13:T13)-B13 -> -80000
A14: =Budget1!A14 -> Rammed Earth | B14: =Budget1!C14 -> 50000 | C14: =sum(D14:T14)-B14 -> -50000
A15: =Budget1!A15 -> Exterior Glass | B15: =Budget1!C15 -> 115000 | C15: =sum(D15:T15)-B15 -> -115000
A16: =Budget1!A16 -> Rammed earth Material | B16: =Budget1!C16 -> 45000 | C16: =sum(D16:T16)-B16 -> -45000
A17: =Budget1!A17 -> Railing | B17: =Budget1!C17 -> 46000 | C17: =sum(D17:T17)-B17 -> -46000
A18: =Budget1!A18 -> Range | B18: =Budget1!C18 -> 95000 | C18: =sum(D18:T18)-B18 -> -95000
A19: =Budget1!A19 -> Permiting | B19: =Budget1!C19
A20: =Budget1!A20 -> Facilities | B20: =Budget1!C20 -> 10000 | C20: =sum(D20:T20)-B20 -> -10000
A21: =Budget1!A21 -> Permits | B21: =Budget1!C21 -> 30000 | C21: =sum(D21:T21)-B21 -> -29275 | D21: =675+50 -> 725
A22: =Budget1!A22 -> Builders Risk | B22: =Budget1!C22 -> 5000 | C22: =sum(D22:T22)-B22 -> -5000
A23: =Budget1!A23 -> Manual J | B23: =Budget1!C23 -> 1500 | C23: =sum(D23:T23)-B23 -> -1500
A24: =Budget1!A24 -> Plans | B24: =Budget1!C24 -> 1000 | C24: =sum(D24:T24)-B24 -> -1000
A25: =Budget1!A25 -> Soil | B25: =Budget1!C25 -> 3000 | C25: =sum(D25:T25)-B25 -> -3000
A26: =Budget1!A26 -> Inspections | B26: =Budget1!C26 -> 2500 | C26: =sum(D26:T26)-B26 -> -2500
A27: =Budget1!A27 -> Site Utilities | B27: =Budget1!C27
A28: =Budget1!A28 -> Site Utilities | B28: =Budget1!C28 -> 122000 | C28: =sum(D28:T28)-B28 -> -122000
A29: =Budget1!A30 -> Gas | B29: =Budget1!C30 -> 10000 | C29: =sum(D29:T29)-B29 -> -10000
A30: =Budget1!A31 -> Power | B30: =Budget1!C31 -> 5000 | C30: =sum(D30:T30)-B30 -> -5000
A31: =Budget1!A32 -> Water | B31: =Budget1!C32 -> 5000 | C31: =sum(D31:T31)-B31 -> -5000
A32: =Budget1!A33 -> Structural | B32: =Budget1!C33
A33: =Budget1!A34 -> Ftgs | B33: =Budget1!C34 -> 35710.41 | C33: =sum(D33:T33)-B33 -> -35710.41
A34: =Budget1!A35 -> Wall | B34: =Budget1!C35 -> 63078 | C34: =sum(D34:T34)-B34 -> -63078
A35: =Budget1!A36 -> Slab | B35: =Budget1!C36 -> 49345.1 | C35: =sum(D35:T35)-B35 -> -49345.1
A36: =Budget1!A37 -> Pan | B36: =Budget1!C37 -> 32075 | C36: =sum(D36:T36)-B36 -> -32075
A37: =Budget1!A38 -> Site | B37: =Budget1!C38 -> 9640 | C37: =sum(D37:T37)-B37 -> -9640
A38: =Budget1!A39 -> Pretreat | B38: =Budget1!C39 -> 1000 | C38: =sum(D38:T38)-B38 -> -1000
A39: =Budget1!A40 -> Steel | B39: =Budget1!C40 -> 184000 | C39: =sum(D39:T39)-B39 -> -184000
A40: =Budget1!A41 -> Lumber | B40: =Budget1!C41 -> 50000 | C40: =sum(D40:T40)-B40 -> -50000
A41: =Budget1!A42 -> Framing Labor | B41: =Budget1!C42 -> 80600 | C41: =sum(D41:T41)-B41 -> -80600
A42: =Budget1!A43 -> Truss | B42: =Budget1!C43 -> 40000 | C42: =sum(D42:T42)-B42 -> -40000
A43: =Budget1!A44 -> Mechanical Rough | B43: =Budget1!C44
A44: =Budget1!A45 -> HVAC/ERV | B44: =Budget1!C45 -> 32000 | C44: =sum(D44:T44)-B44 -> -32000
A45: =Budget1!A46 -> Plumbing/Gas | B45: =Budget1!C46 -> 25000 | C45: =sum(D45:T45)-B45 -> -25000
A46: =Budget1!A47 -> Electrical | B46: =Budget1!C47 -> 45000 | C46: =sum(D46:T46)-B46 -> -45000
A47: =Budget1!A48 -> AV | B47: =Budget1!C48 -> 80000 | C47: =sum(D47:T47)-B47 -> -80000
A48: =Budget1!A49 -> Solar | B48: =Budget1!C49 -> 25000 | C48: =sum(D48:T48)-B48 -> -25000
A49: =Budget1!A50 -> Fireplace | B49: =Budget1!C50 -> 22500 | C49: =sum(D49:T49)-B49 -> -22500
A50: =Budget1!A51 -> Exterior Sealing | B50: =Budget1!C51
A51: =Budget1!A52 -> Roofing | B51: =Budget1!C52 -> 35000 | C51: =sum(D51:T51)-B51 -> -35000
A52: =Budget1!A53 -> Coatings | B52: =Budget1!C53 -> 102000 | C52: =sum(D52:T52)-B52 -> -102000
A53: =Budget1!A54 -> Exterior Glass | B53: =Budget1!C54 -> 115000 | C53: =sum(D53:T53)-B53 -> -115000
A54: =Budget1!A55 -> Exterior Doors | B54: =Budget1!C55 -> 13000 | C54: =sum(D54:T54)-B54 -> -13000
A55: =Budget1!A56 -> Garage Door | B55: =Budget1!C56 -> 22500 | C55: =sum(D55:T55)-B55 -> -22500
A56: =Budget1!A57 -> Exterior Stucco | B56: =Budget1!C57 -> 60000 | C56: =sum(D56:T56)-B56 -> -60000
A57: =Budget1!A58 -> Stone Veneer | B57: =Budget1!C58 -> 30000 | C57: =sum(D57:T57)-B57 -> -30000
A58: =Budget1!A59 -> Rammed Earth | B58: =Budget1!C59 -> 50000 | C58: =sum(D58:T58)-B58 -> -50000
A59: =Budget1!A60 -> Wall/Cieling Finish | B59: =Budget1!C60
A60: =Budget1!A61 -> Insulation | B60: =Budget1!C61 -> 40000 | C60: =sum(D60:T60)-B60 -> -40000
A61: =Budget1!A62 -> Sheetrock | B61: =Budget1!C62 -> 41500 | C61: =sum(D61:T61)-B61 -> -41500
A62: =Budget1!A63 -> Paint | B62: =Budget1!C63 -> 23000 | C62: =sum(D62:T62)-B62 -> -23000
A63: =Budget1!A64 -> Tile Labor | B63: =Budget1!C64 -> 53000 | C63: =sum(D63:T63)-B63 -> -53000
A64: =Budget1!A65 -> Carpentery | B64: =Budget1!C65
A65: =Budget1!A66 -> Cabinet | B65: =Budget1!C66 -> 26000 | C65: =sum(D65:T65)-B65 -> -26000
A66: =Budget1!A67 -> Countertops | B66: =Budget1!C67 -> 45000 | C66: =sum(D66:T66)-B66 -> -45000
A67: =Budget1!A68 -> Finish Carpentry | B67: =Budget1!C68 -> 12000 | C67: =sum(D67:T67)-B67 -> -12000
A68: =Budget1!A69 -> Door | B68: =Budget1!C69 -> 28500 | C68: =sum(D68:T68)-B68 -> -28500
A69: =Budget1!A70 -> Base&Case | B69: =Budget1!C70 -> 5000 | C69: =sum(D69:T69)-B69 -> -5000
A70: =Budget1!A71 -> Door & Bath Hardware | B70: =Budget1!C71 -> 5000 | C70: =sum(D70:T70)-B70 -> -5000
A71: =Budget1!A72 -> Entry Stair | B71: =Budget1!C72 -> 17000 | C71: =sum(D71:T71)-B71 -> -17000
A72: =Budget1!A73 -> Wood Stair | B72: =Budget1!C73 -> 5000 | C72: =sum(D72:T72)-B72 -> -5000
A73: =Budget1!A74 -> Stair Labor | B73: =Budget1!C74 -> 10000 | C73: =sum(D73:T73)-B73 -> -10000
A74: =Budget1!A75 -> Vault Door | B74: =Budget1!C75 -> 7500 | C74: =sum(D74:T74)-B74 -> -7500
A75: =Budget1!A76 -> Hidden Door | B75: =Budget1!C76 -> 25000 | C75: =sum(D75:T75)-B75 -> -25000
A76: =Budget1!A77 -> Equipment/ Finishes | B76: =Budget1!C77
A77: =Budget1!A78 -> HVAC/ERV | B77: =Budget1!C78 -> 21500 | C77: =sum(D77:T77)-B77 -> -21500
A78: =Budget1!A79 -> Plumbing/Gas | B78: =Budget1!C79 -> 32000 | C78: =sum(D78:T78)-B78 -> -32000
A79: =Budget1!A80 -> Electrical | B79: =Budget1!C80 -> 45000 | C79: =sum(D79:T79)-B79 -> -45000
A80: =Budget1!A81 -> AV | B80: =Budget1!C81 -> 80000 | C80: =sum(D80:T80)-B80 -> -80000
A81: =Budget1!A82 -> Range | B81: =Budget1!C82 -> 95000 | C81: =sum(D81:T81)-B81 -> -95000
A82: =Budget1!A83 -> Appliance | B82: =Budget1!C83 -> 48000 | C82: =sum(D82:T82)-B82 -> -48000
A83: =Budget1!A84 -> Glass | B83: =Budget1!C84 -> 7500 | C83: =sum(D83:T83)-B83 -> -7500
A84: =Budget1!A85 -> Railing | B84: =Budget1!C85 -> 46000 | C84: =sum(D84:T84)-B84 -> -46000
A85: =Budget1!A86 -> Outdoor | B85: =Budget1!C86 -> 60000 | C85: =sum(D85:T85)-B85 -> -60000
A86: =Budget1!A87 -> Cleaning | B86: =Budget1!C87 -> 5000 | C86: =sum(D86:T86)-B86 -> -5000
A87: =Budget1!A88 -> Landscape | B87: =Budget1!C88
A88: =Budget1!A89 -> Solar | B88: =Budget1!C89 -> 25000 | C88: =sum(D88:T88)-B88 -> -25000
A89: =Budget1!A90 -> Landscape | B89: =Budget1!C90 | C89: =sum(D89:T89)-B89 -> 0
A90: =Budget1!A91 -> Pavers | B90: =Budget1!C91 -> 28000 | C90: =sum(D90:T90)-B90 -> -28000
B91: =Budget1!C92 | C91: =sum(D91:T91)-B91 -> 0
A92: =Budget1!A93 -> Options | B92: =Budget1!C93
A93: =Budget1!A94 -> Steam | B93: =Budget1!C94
A94: =Budget1!A95 -> Floor Heat | B94: =Budget1!C95
A95: =Budget1!A96 | D95: =Budget1!D114
A96: =Budget1!A97 | D96: =Budget1!D115
A97: =Budget1!A98 | D97: =Budget1!D116
A98: =Budget1!A99
A99: =Budget1!A100
A100: =Budget1!A101
...

Sheet Budget
A1: Trade | B1: Sub | D1: Bid Amount | F1: Comment
A2: Total
A3: Lot 34
A4: Sq Ft | B4: 2345
A5: Cost per Ft. | B5: =D7/B4 -> 0
A6: LTV | B6: =G12/D8 -> 0
A8: Gross | B8: 0.15 | D8: =sum(D9:D14) -> 295216.99 | F8: =sum(F9:F14) -> 723091.55 | G8: 785000 | H8: 0.7
A9: Realtor | B9: 0.05 | D9: 40000 | F9: =G8*B9 -> 39250
A10: Profit | B10: 0.1 | D10: 80000
A12: Land | D12: 175000 | F12: =D12 -> 175000
A14: Build Cost | D14: =sum(D15:D83) -> 216.99 | F14: =sum(F15:F83) -> 508841.55 | G14: =G8*H8 -> 549500
A15: Interest | F15: =D15
A16: Origination | B16: 0.01 | F16: =D16
A18: Contingency
A19: Facilities | D19: 1.81 | F19: =$B$4*D19 -> 4244.45
A20: Engineering | D20: 1.27 | F20: =$B$4*D20 -> 2978.15
A21: Permits | B21: City of Hurricane | D21: 6.4 | F21: =$B$4*D21 -> 15008
A22: Builder Risk | D22: 1.81 | F22: =$B$4*D22 -> 4244.45
A23: Legal | D23: 1.81 | F23: =$B$4*D23 -> 4244.45
A24: WCD | D24: 4.27 | F24: =$B$4*D24 -> 10013.15
A25: Plans | B25: Steamroller | D25: 0.18 | F25: =$B$4*D25 -> 422.1
A26: Recorder | D26: 0.05 | F26: =$B$4*D26 -> 117.25
A27: Soil | B27: Landmark | D27: 0.54 | F27: =$B$4*D27 -> 1266.3
A28: Inspections | D28: 0.54 | F28: =$B$4*D28 -> 1266.3
A29: SWPPP | D29: 0.54 | F29: =$B$4*D29 -> 1266.3
A31: Pad Prep | D31: 2.72 | F31: =$B$4*D31 -> 6378.4
A32: Concrete | B32: Dixie, Ceasar, Sunset | D32: 12.69 | F32: =$B$4*D32 -> 29758.05
A33: Pretreat | B33: Morgan Pest Control | D33: 0.27 | F33: =$B$4*D33 -> 633.15
A34: Lumber | B34: Sunpro | D34: 7.25 | F34: =$B$4*D34 -> 17001.25
A35: Framing Labor | B35: BW, 5 DI, Bud | D35: 9.07 | F35: =$B$4*D35 -> 21269.15
A36: Truss | B36: SGT Truss | D36: 5.44 | F36: =$B$4*D36 -> 12756.8
F37: =$B$4*D37 -> 0
A38: Plumbing/Gas | B38: Bringhurst, Master | D38: 9.95 | F38: =$B$4*D38 -> 23332.75
A39: Plumbing Fixtures | B39: RAC | D39: 2.99 | F39: =$B$4*D39 -> 7011.55
A40: Water Heater | B40: RAC | F40: =$B$4*D40 -> 0
A41: Water Filtration | B41: Advanced | D41: 2.86 | F41: =$B$4*D41 -> 6706.7
A42: HVAC | B42: Kuhn's/Crofts | D42: 5.73 | F42: =$B$4*D42 -> 13436.85
A43: Fireplace | B43: Dixie | D43: 2.56 | F43: =$B$4*D43 -> 6003.2
A44: Electrical | B44: DHE.Copper.Breck | D44: 7.25 | F44: =$B$4*D44 -> 17001.25
A45: Electrical Fixtures | B45: RAC | D45: 3.63 | F45: =$B$4*D45 -> 8512.35
F46: =$B$4*D46 -> 0
A47: Roofing | B47: Pierce | D47: 10.88 | F47: =$B$4*D47 -> 25513.6
A48: Windows | B48: LP | D48: 9.79 | F48: =$B$4*D48 -> 22957.55
A49: Entry Door | D49: 2.72 | F49: =$B$4*D49 -> 6378.4
A50: Exterior Doors | B50: Sunpro | D50: 1.28 | F50: =$B$4*D50 -> 3001.6
A51: Rainscreen | B51: RAC | D51: 1.09 | F51: =$B$4*D51 -> 2556.05
A52: Exterior Stucco | B52: D&D | D52: 10.73 | F52: =$B$4*D52 -> 25161.85
A53: Stone Veneer | B53: Kent | D53: 5.44 | F53: =$B$4*D53 -> 12756.8
F54: =$B$4*D54 -> 0
A55: Insulation | B55: LP | D55: 5.44 | F55: =$B$4*D55 -> 12756.8
A56: Shadow Trim | B56: RAC | D56: 0.91 | F56: =$B$4*D56 -> 2133.95
A57: Finish Carpentry | B57: A&L | D57: 1.27 | F57: =$B$4*D57 -> 2978.15
A58: Sheetrock | B58: D&D | D58: 9.03 | F58: =$B$4*D58 -> 21175.35
A59: Flooring/Tile | B59: Potter | D59: 5.44 | F59: =$B$4*D59 -> 12756.8
A60: Floor Polish | B60: KC | D60: 0.64 | F60: =$B$4*D60 -> 1500.8
A61: Floor Protection | B61: RAC | D61: 0.64 | F61: =$B$4*D61 -> 1500.8
A62: Paint | B62: D&D | D62: 3.44 | F62: =$B$4*D62 -> 8066.8
F63: =$B$4*D63 -> 0
A64: Garage Door | B64: Jesco | D64: 3.36 | F64: =$B$4*D64 -> 7879.2
A65: Cabinet | B65: Boardwalk | D65: 14.51 | F65: =$B$4*D65 -> 34025.95
A66: Countertops | B66: Countertop source | D66: 5.44 | F66: =$B$4*D66 -> 12756.8
A67: Interior Door | B67: Sunpro | D67: 3.2 | F67: =$B$4*D67 -> 7504
A68: Interior trim material | B68: Sunpro | D68: 1.49 | F68: =$B$4*D68 -> 3494.05
A69: Door & Bath Hardware | B69: Sunpro | D69: 1.07 | F69: =$B$4*D69 -> 2509.15
A70: Closet | B70: A&L | D70: 1.81 | F70: =$B$4*D70 -> 4244.45
F71: =$B$4*D71 -> 0
A72: Glass | B72: Desert | D72: 1.81 | F72: =$B$4*D72 -> 4244.45
A73: Painted Glass | B73: Desert | D73: 2.72 | F73: =$B$4*D73 -> 6378.4
A74: Stretch | B74: RAC/H&E | D74: 1.81 | F74: =$B$4*D74 -> 4244.45
A75: Alabaser | B75: RAC/Desert | D75: 2.13 | F75: =$B$4*D75 -> 4994.85
A76: Salt | B76: RAC/Quick | D76: 2.13 | F76: =$B$4*D76 -> 4994.85
F77: =$B$4*D77 -> 0
A78: Cleaning | B78: Laura | D78: 0.91 | F78: =$B$4*D78 -> 2133.95
A79: Appliance | B79: Ferguson's | D79: 6.53 | F79: =$B$4*D79 -> 15312.85
F80: =$B$4*D80 -> 0
A81: Exterior concrete | B81: Dixie, Ceasar, Sunset | D81: 4.07 | F81: =$B$4*D81 -> 9544.15
A82: Landscape | B82: Bruce | D82: 3.63 | F82: =$B$4*D82 -> 8512.35
